Workbook

Sheet Resumen
A1: APRENDIZAJE SUPERVISADO — SEGUIMIENTO DE ESTUDIO | J1: TODOS LOS TEMAS DEL CURSO — 34 temas (nivel 0 y 1, los 5 bloques)
J2: Código | K2: Bloque | L2: Tema | M2: Estado | N2: Prioridad
A3: Plan de estudio generado a partir de los resúmenes de clase (temas 1-5) y organizado según la metodología de tutor de aprendizaje acelerado v11. Todos los conceptos parten en estado Pendiente: actualízalos durante las sesiones de estudio reales con el prompt maestro de la carpeta resumen. | J3: ='Mapa de estudio'!A2 -> 1 | K3: =LEFT(J3,FIND(".",J3&".")-1) -> 1 | L3: ='Mapa de estudio'!C2 -> FUNDAMENTOS Y PREPARACIÓN DE DATOS | M3: ='Mapa de estudio'!E2 -> 🟢 Comprendido | N3: ='Mapa de estudio'!H2 -> Alta
J4: ='Mapa de estudio'!A3 -> 1.1 | K4: =LEFT(J4,FIND(".",J4&".")-1) -> 1 | L4: ='Mapa de estudio'!C3 -> Metodología CRISP-DM | M4: ='Mapa de estudio'!E3 -> 🟢 Comprendido | N4: ='Mapa de estudio'!H3 -> Alta
A5: Total conceptos | C5: Comprendidos / firmes | E5: Pendientes | G5: Débiles | J5: ='Mapa de estudio'!A11 -> 1.2 | K5: =LEFT(J5,FIND(".",J5&".")-1) -> 1 | L5: ='Mapa de estudio'!C11 -> Tipos de aprendizaje (supervisado / no supervisado / otros) | M5: ='Mapa de estudio'!E11 -> 🟢 Comprendido | N5: ='Mapa de estudio'!H11 -> Alta
A6: =COUNTA('Mapa de estudio'!$A$2:$A$186) -> 185 | C6: =COUNTIF('Mapa de estudio'!$E$2:$E$186,"🟢 Firme")+COUNTIF('Mapa de estudio'!$E$2:$E$186,"🟢 Comprendido") -> 54 | E6: =COUNTIF('Mapa de estudio'!$E$2:$E$186,"⚪ Pendiente") -> 121 | G6: =COUNTIF('Mapa de estudio'!$E$2:$E$186,"🔴 Débil") -> 4 | J6: ='Mapa de estudio'!A18 -> 1.3 | K6: =LEFT(J6,FIND(".",J6&".")-1) -> 1 | L6: ='Mapa de estudio'!C18 -> Estructura de datos: instancias, atributos y clase | M6: ='Mapa de estudio'!E18 -> 🟢 Comprendido | N6: ='Mapa de estudio'!H18 -> Alta
J7: ='Mapa de estudio'!A25 -> 1.4 | K7: =LEFT(J7,FIND(".",J7&".")-1) -> 1 | L7: ='Mapa de estudio'!C25 -> Limpieza de datos — introducción | M7: ='Mapa de estudio'!E25 -> 🟢 Comprendido | N7: ='Mapa de estudio'!H25 -> Media
J8: ='Mapa de estudio'!A28 -> 1.5 | K8: =LEFT(J8,FIND(".",J8&".")-1) -> 1 | L8: ='Mapa de estudio'!C28 -> Normalización y estandarización | M8: ='Mapa de estudio'!E28 -> 🟢 Comprendido | N8: ='Mapa de estudio'!H28 -> Alta
A9: Estado | B9: Cantidad | D9: TEMA EN CURSO — TEMA 1: FUNDAMENTOS Y PREPARACIÓN DE DATOS (ver los 5 temas completos en J:N) | J9: ='Mapa de estudio'!A33 -> 1.6 | K9: =LEFT(J9,FIND(".",J9&".")-1) -> 1 | L9: ='Mapa de estudio'!C33 -> Detección de outliers | M9: ='Mapa de estudio'!E33 -> 🟢 Comprendido | N9: ='Mapa de estudio'!H33 -> Alta
A10: 🟢 Firme | B10: =COUNTIF('Mapa de estudio'!$E$2:$E$186,A10) -> 0 | D10: Concepto | E10: Estado | F10: Idea clave | G10: Siguiente | H10: Prioridad | J10: ='Mapa de estudio'!A39 -> 1.7 | K10: =LEFT(J10,FIND(".",J10&".")-1) -> 1 | L10: ='Mapa de estudio'!C39 -> Imputación de valores ausentes | M10: ='Mapa de estudio'!E39 -> 🔴 Débil | N10: ='Mapa de estudio'!H39 -> Alta
A11: 🟢 Comprendido | B11: =COUNTIF('Mapa de estudio'!$E$2:$E$186,A11) -> 54 | D11: ='Mapa de estudio'!C3 -> Metodología CRISP-DM | E11: ='Mapa de estudio'!E3 -> 🟢 Comprendido | F11: ='Mapa de estudio'!F3&"" -> Es el proceso estándar más usado en minería de datos para estructurar un proyecto de aprendizaje automático, de principio a fin. Tiene 6 fases con dependencias secuenciales y cíclicas (puede haber iteraciones). | G11: ='Mapa de estudio'!G3&"" -> Aplicar las 6 fases a un caso real y ubicar en qué fase encaja cada tarea del curso (limpieza, modelado, evaluación). | H11: ='Mapa de estudio'!H3 -> Alta | J11: ='Mapa de estudio'!A44 -> 1.8 | K11: =LEFT(J11,FIND(".",J11&".")-1) -> 1 | L11: ='Mapa de estudio'!C44 -> Selección de atributos | M11: ='Mapa de estudio'!E44 -> 🟠 Parcial | N11: ='Mapa de estudio'!H44 -> Media
A12: 🟡 Repasar | B12: =COUNTIF('Mapa de estudio'!$E$2:$E$186,A12) -> 5 | D12: ='Mapa de estudio'!C11 -> Tipos de aprendizaje (supervisado / no supervisado / otros) | E12: ='Mapa de estudio'!E11 -> 🟢 Comprendido | F12: ='Mapa de estudio'!F11&"" -> Distinción fundamental: si el dataset tiene una variable de salida es aprendizaje supervisado (predicción/inferencia); si no la tiene, es no supervisado. Existen además variantes intermedias (semisupervisado, refuerzo). | G12: ='Mapa de estudio'!G11&"" -> Practicar clasificando problemas reales como regresión, clasificación, clustering o reglas de asociación. | H12: ='Mapa de estudio'!H11 -> Alta | J12: ='Mapa de estudio'!A50 -> 2 | K12: =LEFT(J12,FIND(".",J12&".")-1) -> 2 | L12: ='Mapa de estudio'!C50 -> VALIDACIÓN DE MODELOS Y MÉTRICAS DE EVALUACIÓN | M12: ='Mapa de estudio'!E50 -> 🟢 Comprendido | N12: ='Mapa de estudio'!H50 -> Alta
A13: 🟠 Iniciado | B13: =COUNTIF('Mapa de estudio'!$E$2:$E$186,A13) -> 0 | D13: ='Mapa de estudio'!C18 -> Estructura de datos: instancias, atributos y clase | E13: ='Mapa de estudio'!E18 -> 🟢 Comprendido | F13: ='Mapa de estudio'!F18&"" -> La tabla de datos (dataset) es la estructura fundamental: filas = instancias, columnas = atributos (más la clase, que es la variable de salida). Notación formal: X (atributos), y (clase). | G13: ='Mapa de estudio'!G18&"" -> Practicar identificando instancias, atributos y clase en un dataset real como iris o penguins. | H13: ='Mapa de estudio'!H18 -> Alta | J13: ='Mapa de estudio'!A51 -> 2.1 | K13: =LEFT(J13,FIND(".",J13&".")-1) -> 2 | L13: ='Mapa de estudio'!C51 -> Introducción: entrenamiento, test, sobreajuste y subajuste | M13: ='Mapa de estudio'!E51 -> 🟢 Comprendido | N13: ='Mapa de estudio'!H51 -> Alta
A14: 🟠 Parcial | B14: =COUNTIF('Mapa de estudio'!$E$2:$E$186,A14) -> 1 | D14: ='Mapa de estudio'!C25 -> Limpieza de datos — introducción | E14: ='Mapa de estudio'!E25 -> 🟢 Comprendido | F14: ='Mapa de estudio'!F25&"" -> Tarea fundamental dentro de la fase de preparación de datos de CRISP-DM: elimina defectos y adapta los datos para que expongan sus patrones con la mayor nitidez posible antes del modelado. | G14: ='Mapa de estudio'!G25&"" -> Repasar junto con las 4 técnicas concretas (normalización, outliers, imputación, selección) que desarrollan esta fase. | H14: ='Mapa de estudio'!H25 -> Media | J14: ='Mapa de estudio'!A57 -> 2.2 | K14: =LEFT(J14,FIND(".",J14&".")-1) -> 2 | L14: ='Mapa de estudio'!C57 -> Validación hold-out | M14: ='Mapa de estudio'!E57 -> 🟢 Comprendido | N14: ='Mapa de estudio'!H57 -> Alta
A15: ⚪ Pendiente | B15: =COUNTIF('Mapa de estudio'!$E$2:$E$186,A15) -> 121 | D15: ='Mapa de estudio'!C28 -> Normalización y estandarización | E15: ='Mapa de estudio'!E28 -> 🟢 Comprendido | F15: ='Mapa de estudio'!F28&"" -> Dos técnicas para llevar los atributos numéricos a una escala común (centrar y escalar), evitando que un atributo con mayor escala domine artificialmente sobre otro de igual importancia real. Fórmula/Cómo: Normalización: x_N=(x-min)/(max-min); Estandarización: x_S=(x-media)/desviación | G15: ='Mapa de estudio'!G28&"" -> Practicar aplicando MinMaxScaler y StandardScaler con fit en train y transform en test. | H15: ='Mapa de estudio'!H28 -> Alta | J15: ='Mapa de estudio'!A62 -> 2.3 | K15: =LEFT(J15,FIND(".",J15&".")-1) -> 2 | L15: ='Mapa de estudio'!C62 -> Validación cruzada / K-fold | M15: ='Mapa de estudio'!E62 -> 🟢 Comprendido | N15: ='Mapa de estudio'!H62 -> Alta
A16: 🔴 Débil | B16: =COUNTIF('Mapa de estudio'!$E$2:$E$186,A16) -> 4 | D16: ='Mapa de estudio'!C33 -> Detección de outliers | E16: ='Mapa de estudio'!E33 -> 🟢 Comprendido | F16: ='Mapa de estudio'!F33&"" -> Identificar valores anómalos fuera de la distribución natural de los datos, que pueden reducir la eficacia de los modelos. El límite entre outlier y no-outlier suele ser difuso. | G16: ='Mapa de estudio'!G33&"" -> Practicar EllipticEnvelope y el método boxplot sobre el dataset outliers.csv. | H16: ='Mapa de estudio'!H33 -> Alta | J16: ='Mapa de estudio'!A68 -> 2.4 | K16: =LEFT(J16,FIND(".",J16&".")-1) -> 2 | L16: ='Mapa de estudio'!C68 -> Ajuste de parámetros y validación anidada | M16: ='Mapa de estudio'!E68 -> ⚪ Pendiente | N16: ='Mapa de estudio'!H68 -> Alta
D17: ='Mapa de estudio'!C39 -> Imputación de valores ausentes | E17: ='Mapa de estudio'!E39 -> 🔴 Débil | F17: ='Mapa de estudio'!F39&"" -> Reemplazar valores ausentes (missing values / NaN) por valores estimados, en vez de eliminar instancias completas, para no perder información. | G17: ='Mapa de estudio'!G39&"" -> Practicar SimpleImputer sobre datos reales (penguins.csv) con fit/transform. | H17: ='Mapa de estudio'!H39 -> Alta | J17: ='Mapa de estudio'!A73 -> 2.5 | K17: =LEFT(J17,FIND(".",J17&".")-1) -> 2 | L17: ='Mapa de estudio'!C73 -> Evaluación en regresión: MAE, MSE, RMSE, MAPE | M17: ='Mapa de estudio'!E73 -> ⚪ Pendiente | N17: ='Mapa de estudio'!H73 -> Alta
D18: ='Mapa de estudio'!C44 -> Selección de atributos | E18: ='Mapa de estudio'!E44 -> 🟠 Parcial | F18: ='Mapa de estudio'!F44&"" -> Subtarea de la reducción de dimensionalidad: elimina atributos poco útiles usando un algoritmo de evaluación que mide su 'bondad', ya sea de forma individual (univariante) o en conjunto (multivariante). | G18: ='Mapa de estudio'!G44&"" -> Practicar VarianceThreshold, f_regression y mutual_info_regression sobre datos sintéticos y iris. | H18: ='Mapa de estudio'!H44 -> Media | J18: ='Mapa de estudio'!A79 -> 2.6 | K18: =LEFT(J18,FIND(".",J18&".")-1) -> 2 | L18: ='Mapa de estudio'!C79 -> Evaluación en clasificación: matriz de confusión, precisión, sensibilidad, F1, accuracy | M18: ='Mapa de estudio'!E79 -> ⚪ Pendiente | N18: ='Mapa de estudio'!H79 -> Alta
J19: ='Mapa de estudio'!A87 -> 3 | K19: =LEFT(J19,FIND(".",J19&".")-1) -> 3 | L19: ='Mapa de estudio'!C87 -> EXTRACCIÓN DE CARACTERÍSTICAS (VARIABLES E IMÁGENES) | M19: ='Mapa de estudio'!E87 -> ⚪ Pendiente | N19: ='Mapa de estudio'!H87 -> Alta
A20: Criterio de avance: ningún concepto se marca como dominado solo por haberlo leído aquí. Este mapa es un plan de estudio inicial (todo en Pendiente); el estado real se actualiza durante las sesiones de tutoría aplicando la regla 11 del prompt v11 (diagnóstico continuo: dominado = resuelvo con él un problema nuevo). | J20: ='Mapa de estudio'!A88 -> 3.1 | K20: =LEFT(J20,FIND(".",J20&".")-1) -> 3 | L20: ='Mapa de estudio'!C88 -> Conceptos básicos y variable estadística | M20: ='Mapa de estudio'!E88 -> ⚪ Pendiente | N20: ='Mapa de estudio'!H88 -> Media
J21: ='Mapa de estudio'!A93 -> 3.2 | K21: =LEFT(J21,FIND(".",J21&".")-1) -> 3 | L21: ='Mapa de estudio'!C93 -> Análisis de variables cualitativas | M21: ='Mapa de estudio'!E93 -> ⚪ Pendiente | N21: ='Mapa de estudio'!H93 -> Media
A22: PROGRESO POR BLOQUE — LOS 5 TEMAS DEL CURSO | J22: ='Mapa de estudio'!A96 -> 3.3 | K22: =LEFT(J22,FIND(".",J22&".")-1) -> 3 | L22: ='Mapa de estudio'!C96 -> Análisis de variables cuantitativas | M22: ='Mapa de estudio'!E96 -> ⚪ Pendiente | N22: ='Mapa de estudio'!H96 -> Alta
A23: Bloque | B23: Total | C23: 🟢 Dominado | D23: 🟠 En progreso | E23: 🟡 Repasar | F23: ⚪ Pendiente | G23: 🔴 Débil | H23: % Dominado | J23: ='Mapa de estudio'!A101 -> 3.4 | K23: =LEFT(J23,FIND(".",J23&".")-1) -> 3 | L23: ='Mapa de estudio'!C101 -> Introducción a los datos 2D (la imagen como dato) | M23: ='Mapa de estudio'!E101 -> ⚪ Pendiente | N23: ='Mapa de estudio'!H101 -> Alta
A24: 1. Fundamentos y preparación de datos | B24: =COUNTIF('Mapa de estudio'!$B$2:$B$186,$A24) -> 48 | C24: =COUNTIFS('Mapa de estudio'!$B$2:$B$186,$A24,'Mapa de estudio'!$E$2:$E$186,"🟢 Firme")+COUNTIFS('Mapa de estudio'!$B$2:$B$186,$A24,'Mapa de estudio'!$E$2:$E$186,"🟢 Comprendido") -> 38 | D24: =COUNTIFS('Mapa de estudio'!$B$2:$B$186,$A24,'Mapa de estudio'!$E$2:$E$186,"🟠 Iniciado")+COUNTIFS('Mapa de estudio'!$B$2:$B$186,$A24,'Mapa de estudio'!$E$2:$E$186,"🟠 Parcial") -> 1 | E24: =COUNTIFS('Mapa de estudio'!$B$2:$B$186,$A24,'Mapa de estudio'!$E$2:$E$186,"🟡 Repasar") -> 5 | F24: =COUNTIFS('Mapa de estudio'!$B$2:$B$186,$A24,'Mapa de estudio'!$E$2:$E$186,"⚪ Pendiente") -> 0 | G24: =COUNTIFS('Mapa de estudio'!$B$2:$B$186,$A24,'Mapa de estudio'!$E$2:$E$186,"🔴 Débil") -> 4 | H24: =IFERROR(C24/B24,0) -> 0.79166667 | J24: ='Mapa de estudio'!A102 -> 3.5 | K24: =LEFT(J24,FIND(".",J24&".")-1) -> 3 | L24: ='Mapa de estudio'!C102 -> Procesado de imagen: transformaciones de intensidad | M24: ='Mapa de estudio'!E102 -> ⚪ Pendiente | N24: ='Mapa de estudio'!H102 -> Media
A25: 2. Validación de modelos y métricas | B25: =COUNTIF('Mapa de estudio'!$B$2:$B$186,$A25) -> 37 | C25: =COUNTIFS('Mapa de estudio'!$B$2:$B$186,$A25,'Mapa de estudio'!$E$2:$E$186,"🟢 Firme")+COUNTIFS('Mapa de estudio'!$B$2:$B$186,$A25,'Mapa de estudio'!$E$2:$E$186,"🟢 Comprendido") -> 16 | D25: =COUNTIFS('Mapa de estudio'!$B$2:$B$186,$A25,'Mapa de estudio'!$E$2:$E$186,"🟠 Iniciado")+COUNTIFS('Mapa de estudio'!$B$2:$B$186,$A25,'Mapa de estudio'!$E$2:$E$186,"🟠 Parcial") -> 0 | E25: =COUNTIFS('Mapa de estudio'!$B$2:$B$186,$A25,'Mapa de estudio'!$E$2:$E$186,"🟡 Repasar") -> 0 | F25: =COUNTIFS('Mapa de estudio'!$B$2:$B$186,$A25,'Mapa de estudio'!$E$2:$E$186,"⚪ Pendiente") -> 21 | G25: =COUNTIFS('Mapa de estudio'!$B$2:$B$186,$A25,'Mapa de estudio'!$E$2:$E$186,"🔴 Débil") -> 0 | H25: =IFERROR(C25/B25,0) -> 0.43243243 | J25: ='Mapa de estudio'!A106 -> 3.6 | K25: =LEFT(J25,FIND(".",J25&".")-1) -> 3 | L25: ='Mapa de estudio'!C106 -> Procesado de imagen: espacios de color y transformaciones geométricas | M25: ='Mapa de estudio'!E106 -> ⚪ Pendiente | N25: ='Mapa de estudio'!H106 -> Media
A26: 3. Extracción de características | B26: =COUNTIF('Mapa de estudio'!$B$2:$B$186,$A26) -> 39 | C26: =COUNTIFS('Mapa de estudio'!$B$2:$B$186,$A26,'Mapa de estudio'!$E$2:$E$186,"🟢 Firme")+COUNTIFS('Mapa de estudio'!$B$2:$B$186,$A26,'Mapa de estudio'!$E$2:$E$186,"🟢 Comprendido") -> 0 | D26: =COUNTIFS('Mapa de estudio'!$B$2:$B$186,$A26,'Mapa de estudio'!$E$2:$E$186,"🟠 Iniciado")+COUNTIFS('Mapa de estudio'!$B$2:$B$186,$A26,'Mapa de estudio'!$E$2:$E$186,"🟠 Parcial") -> 0 | E26: =COUNTIFS('Mapa de estudio'!$B$2:$B$186,$A26,'Mapa de estudio'!$E$2:$E$186,"🟡 Repasar") -> 0 | F26: =COUNTIFS('Mapa de estudio'!$B$2:$B$186,$A26,'Mapa de estudio'!$E$2:$E$186,"⚪ Pendiente") -> 39 | G26: =COUNTIFS('Mapa de estudio'!$B$2:$B$186,$A26,'Mapa de estudio'!$E$2:$E$186,"🔴 Débil") -> 0 | H26: =IFERROR(C26/B26,0) -> 0 | J26: ='Mapa de estudio'!A111 -> 3.7 | K26: =LEFT(J26,FIND(".",J26&".")-1) -> 3 | L26: ='Mapa de estudio'!C111 -> Segmentación de imágenes | M26: ='Mapa de estudio'!E111 -> ⚪ Pendiente | N26: ='Mapa de estudio'!H111 -> Alta
A27: 4. Modelos de regresión | B27: =COUNTIF('Mapa de estudio'!$B$2:$B$186,$A27) -> 27 | C27: =COUNTIFS('Mapa de estudio'!$B$2:$B$186,$A27,'Mapa de estudio'!$E$2:$E$186,"🟢 Firme")+COUNTIFS('Mapa de estudio'!$B$2:$B$186,$A27,'Mapa de estudio'!$E$2:$E$186,"🟢 Comprendido") -> 0 | D27: =COUNTIFS('Mapa de estudio'!$B$2:$B$186,$A27,'Mapa de estudio'!$E$2:$E$186,"🟠 Iniciado")+COUNTIFS('Mapa de estudio'!$B$2:$B$186,$A27,'Mapa de estudio'!$E$2:$E$186,"🟠 Parcial") -> 0 | E27: =COUNTIFS('Mapa de estudio'!$B$2:$B$186,$A27,'Mapa de estudio'!$E$2:$E$186,"🟡 Repasar") -> 0 | F27: =COUNTIFS('Mapa de estudio'!$B$2:$B$186,$A27,'Mapa de estudio'!$E$2:$E$186,"⚪ Pendiente") -> 27 | G27: =COUNTIFS('Mapa de estudio'!$B$2:$B$186,$A27,'Mapa de estudio'!$E$2:$E$186,"🔴 Débil") -> 0 | H27: =IFERROR(C27/B27,0) -> 0 | J27: ='Mapa de estudio'!A116 -> 3.8 | K27: =LEFT(J27,FIND(".",J27&".")-1) -> 3 | L27: ='Mapa de estudio'!C116 -> Descriptores de forma (descriptores geométricos) | M27: ='Mapa de estudio'!E116 -> ⚪ Pendiente | N27: ='Mapa de estudio'!H116 -> Alta
A28: 5. Modelos de clasificación | B28: =COUNTIF('Mapa de estudio'!$B$2:$B$186,$A28) -> 34 | C28: =COUNTIFS('Mapa de estudio'!$B$2:$B$186,$A28,'Mapa de estudio'!$E$2:$E$186,"🟢 Firme")+COUNTIFS('Mapa de estudio'!$B$2:$B$186,$A28,'Mapa de estudio'!$E$2:$E$186,"🟢 Comprendido") -> 0 | D28: =COUNTIFS('Mapa de estudio'!$B$2:$B$186,$A28,'Mapa de estudio'!$E$2:$E$186,"🟠 Iniciado")+COUNTIFS('Mapa de estudio'!$B$2:$B$186,$A28,'Mapa de estudio'!$E$2:$E$186,"🟠 Parcial") -> 0 | E28: =COUNTIFS('Mapa de estudio'!$B$2:$B$186,$A28,'Mapa de estudio'!$E$2:$E$186,"🟡 Repasar") -> 0 | F28: =COUNTIFS('Mapa de estudio'!$B$2:$B$186,$A28,'Mapa de estudio'!$E$2:$E$186,"⚪ Pendiente") -> 34 | G28: =COUNTIFS('Mapa de estudio'!$B$2:$B$186,$A28,'Mapa de estudio'!$E$2:$E$186,"🔴 Débil") -> 0 | H28: =IFERROR(C28/B28,0) -> 0 | J28: ='Mapa de estudio'!A120 -> 3.9 | K28: =LEFT(J28,FIND(".",J28&".")-1) -> 3 | L28: ='Mapa de estudio'!C120 -> Descriptores de textura | M28: ='Mapa de estudio'!E120 -> ⚪ Pendiente | N28: ='Mapa de estudio'!H120 -> Alta
A29: TOTAL CURSO | B29: =SUM(B24:B28) -> 185 | C29: =SUM(C24:C28) -> 54 | D29: =SUM(D24:D28) -> 1 | E29: =SUM(E24:E28) -> 5 | F29: =SUM(F24:F28) -> 121 | G29: =SUM(G24:G28) -> 4 | H29: =IFERROR(C29/B29,0) -> 0.29189189 | J29: ='Mapa de estudio'!A126 -> 4 | K29: =LEFT(J29,FIND(".",J29&".")-1) -> 4 | L29: ='Mapa de estudio'!C126 -> MODELOS DE REGRESIÓN | M29: ='Mapa de estudio'!E126 -> ⚪ Pendiente | N29: ='Mapa de estudio'!H126 -> Alta
A30: Orden pedagógico del curso: Bloque 1 → 2 → 3 → 4 → 5 (respeta el orden real de las carpetas tema1-tema5 del repositorio). El bloque 3 (Extracción de características) va antes de los modelos de regresión/clasificación porque construye las variables/features que luego usan los temas 4 y 5. Ninguno está iniciado todavía. | J30: ='Mapa de estudio'!A127 -> 4.1 | K30: =LEFT(J30,FIND(".",J30&".")-1) -> 4 | L30: ='Mapa de estudio'!C127 -> Regresión lineal múltiple (OLS) | M30: ='Mapa de estudio'!E127 -> ⚪ Pendiente | N30: ='Mapa de estudio'!H127 -> Alta
J31: ='Mapa de estudio'!A138 -> 4.2 | K31: =LEFT(J31,FIND(".",J31&".")-1) -> 4 | L31: ='Mapa de estudio'!C138 -> Regresión polinómica | M31: ='Mapa de estudio'!E138 -> ⚪ Pendiente | N31: ='Mapa de estudio'!H138 -> Media
J32: ='Mapa de estudio'!A142 -> 4.3 | K32: =LEFT(J32,FIND(".",J32&".")-1) -> 4 | L32: ='Mapa de estudio'!C142 -> Vecinos más cercanos (KNN) para regresión | M32: ='Mapa de estudio'!E142 -> ⚪ Pendiente | N32: ='Mapa de estudio'!H142 -> Alta
J33: ='Mapa de estudio'!A153 -> 5 | K33: =LEFT(J33,FIND(".",J33&".")-1) -> 5 | L33: ='Mapa de estudio'!C153 -> MODELOS DE CLASIFICACIÓN | M33: ='Mapa de estudio'!E153 -> ⚪ Pendiente | N33: ='Mapa de estudio'!H153 -> Alta
J34: ='Mapa de estudio'!A154 -> 5.1 | K34: =LEFT(J34,FIND(".",J34&".")-1) -> 5 | L34: ='Mapa de estudio'!C154 -> Regresión logística (LOGR) | M34: ='Mapa de estudio'!E154 -> ⚪ Pendiente | N34: ='Mapa de estudio'!H154 -> Alta
J35: ='Mapa de estudio'!A168 -> 5.2 | K35: =LEFT(J35,FIND(".",J35&".")-1) -> 5 | L35: ='Mapa de estudio'!C168 -> Árboles de decisión | M35: ='Mapa de estudio'!E168 -> ⚪ Pendiente | N35: ='Mapa de estudio'!H168 -> Alta
J36: ='Mapa de estudio'!A183 -> 5.3 | K36: =LEFT(J36,FIND(".",J36&".")-1) -> 5 | L36: ='Mapa de estudio'!C183 -> SVM — Support Vector Machines | M36: ='Mapa de estudio'!E183 -> ⚪ Pendiente | N36: ='Mapa de estudio'!H183 -> Media

Sheet Mapa de estudio
A1: Código | B1: Bloque | C1: Tema / concepto | D1: Nivel | E1: Estado | F1: Qué significa / evidencia actual | G1: Siguiente paso | H1: Prioridad | I1: Actualizado | J1: Fuente
A2: 1 | B2: 1. Fundamentos y preparación de datos | C2: FUNDAMENTOS Y PREPARACIÓN DE DATOS | D2: 0 | E2: 🟢 Comprendido | F2: Primer bloque del curso: metodología CRISP-DM para estructurar el proyecto, tipos de aprendizaje, estructura de un dataset (instancias/atributos/clase) y las 4 técnicas de limpieza de datos (normalización/estandarización, outliers, imputación, selección de atributos). Base obligatoria antes de entrenar cualquier modelo. | G2: Repasar CRISP-DM y tipos de aprendizaje primero; luego las 4 técnicas de limpieza en orden (normalización, outliers, imputación, selección). | H2: Alta | I2: 27/09/2026 | J2: resumen_cap1_tema1.txt
A3: 1.1 | B3: 1. Fundamentos y preparación de datos | C3: Metodología CRISP-DM | D3: 1 | E3: 🟢 Comprendido | F3: Es el proceso estándar más usado en minería de datos para estructurar un proyecto de aprendizaje automático, de principio a fin. Tiene 6 fases con dependencias secuenciales y cíclicas (puede haber iteraciones). | G3: Aplicar las 6 fases a un caso real y ubicar en qué fase encaja cada tarea del curso (limpieza, modelado, evaluación). | H3: Alta | I3: 27/09/2026 | J3: resumen_cap1_tema1.txt
A4: 1.1.a | B4: 1. Fundamentos y preparación de datos | C4: Fase 1: Comprensión del negocio | D4: 2 | E4: 🟢 Comprendido | F4: Primera fase, recurrente durante todo el proyecto: determinar objetivos de negocio y criterios de éxito, evaluar la situación actual, traducir objetivos de negocio a metas técnicas y producir un plan de proyecto. | H4: Media | I4: 27/09/2026 | J4: resumen_cap1_tema1.txt
A5: 1.1.b | B5: 1. Fundamentos y preparación de datos | C5: Fase 2: Comprensión de los datos | D5: 2 | E5: 🟢 Comprendido | F5: Recolección y exploración inicial de los datos: describirlos, explorarlos (estadística descriptiva, histogramas) y verificar su calidad (nulos, valores fuera de rango). Reduce el tiempo global del proyecto. | H5: Media | I5: 27/09/2026 | J5: resumen_cap1_tema1.txt
A6: 1.1.c | B6: 1. Fundamentos y preparación de datos | C6: Fase 3: Preparación de los datos | D6: 2 | E6: 🟢 Comprendido | F6: La fase MÁS CRÍTICA: seleccionar, limpiar y construir los datos preparados para el modelado (normalización, outliers, imputación, selección de atributos). Los errores no detectados aquí se arrastran al modelado. | H6: Alta | I6: 27/09/2026 | J6: resumen_cap1_tema1.txt
A7: 1.1.d | B7: 1. Fundamentos y preparación de datos | C7: Fase 4: Modelado | D7: 2 | E7: 🟢 Comprendido | F7: Fase central y foco de la asignatura: seleccionar algoritmos, generar el plan de prueba (parámetros, métricas, validación), construir los modelos y evaluar resultados técnicamente. | H7: Alta | I7: 27/09/2026 | J7: resumen_cap1_tema1.txt
A8: 1.1.e | B8: 1. Fundamentos y preparación de datos | C8: Fase 5: Evaluación de negocio | D8: 2 | E8: 🟢 Comprendido | F8: Se evalúan los modelos frente a los criterios de éxito de negocio definidos al inicio, se revisa el proceso y se decide si finalizar, iterar o abrir nuevos (sub)proyectos. | H8: Media | I8: 27/09/2026 | J8: resumen_cap1_tema1.txt
A9: 1.1.f | B9: 1. Fundamentos y preparación de datos | C9: Fase 6: Despliegue | D9: 2 | E9: 🟢 Comprendido | F9: El conocimiento obtenido se transforma en acciones dentro del negocio: planear implementación, monitorizar y mantener, crear informe final y revisar el proyecto. | H9: Media | I9: 27/09/2026 | J9: resumen_cap1_tema1.txt
A10: 1.1.g | B10: 1. Fundamentos y preparación de datos | C10: Roles en ciencia de datos | D10: 2 | E10: 🟢 Comprendido | F10: Cuatro roles típicos de un equipo de datos: director técnico (data scientist chief), científico de datos (data scientist), analista de datos (data analyst) e ingeniero de datos (data engineer). | H10: Baja | I10: 27/09/2026 | J10: resumen_cap1_tema1.txt
A11: 1.2 | B11: 1. Fundamentos y preparación de datos | C11: Tipos de aprendizaje (supervisado / no supervisado / otros) | D11: 1 | E11: 🟢 Comprendido | F11: Distinción fundamental: si el dataset tiene una variable de salida es aprendizaje supervisado (predicción/inferencia); si no la tiene, es no supervisado. Existen además variantes intermedias (semisupervisado, refuerzo). | G11: Practicar clasificando problemas reales como regresión, clasificación, clustering o reglas de asociación. | H11: Alta | I11: 27/09/2026 | J11: resumen_cap1_tema1.txt
A12: 1.2.a | B12: 1. Fundamentos y preparación de datos | C12: Aprendizaje supervisado: regresión vs. clasificación | D12: 2 | E12: 🟢 Comprendido | F12: Se estima la variable de salida en función del resto. Si la salida es numérica es regresión; si es categórica (etiqueta) es clasificación. Todas las filas deben tener valor en la salida. | H12: Alta | I12: 27/09/2026 | J12: resumen_cap1_tema1.txt
A13: 1.2.b | B13: 1. Fundamentos y preparación de datos | C13: Aprendizaje no supervisado: clustering y reglas de asociación | D13: 2 | E13: 🟢 Comprendido | F13: Sin variable de salida, no es predicción. Clustering agrupa datos similares; reglas de asociación relacionan variables mediante causa-efecto (antecedente/consecuente), útiles para recomendación. | H13: Media | I13: 27/09/2026 | J13: resumen_cap1_tema1.txt
A14: 1.2.c | B14: 1. Fundamentos y preparación de datos | C14: Reducción de dimensionalidad | D14: 2 | E14: 🟢 Comprendido | F14: Puede ser supervisada o no supervisada. Reduce el volumen de datos (filas/columnas o transformando el espacio de valores) buscando mantener la eficacia y aumentar la eficiencia. | H14: Media | I14: 27/09/2026 | J14: resumen_cap1_tema1.txt
A15: 1.2.d | B15: 1. Fundamentos y preparación de datos | C15: Aprendizaje semisupervisado | D15: 2 | E15: 🟢 Comprendido | F15: Hay variable de salida, pero no todas las filas tienen valor para ella. En vez de eliminar esas filas, se construyen modelos que aprovechan todos los datos disponibles. | H15: Baja | I15: 27/09/2026 | J15: resumen_cap1_tema1.txt
A16: 1.2.e | B16: 1. Fundamentos y preparación de datos | C16: Aprendizaje por refuerzo | D16: 2 | E16: 🟢 Comprendido | F16: El algoritmo recibe una valoración sobre su respuesta, no el valor exacto correcto como en supervisado. Cuando acierta se parece a supervisado; cuando falla solo sabe que fue inadecuado. | H16: Baja | I16: 27/09/2026 | J16: resumen_cap1_tema1.txt
A17: 1.2.f | B17: 1. Fundamentos y preparación de datos | C17: Frontera de decisión / frontera bayesiana | D17: 2 | E17: 🟡 Repasar | F17: En el caso ideal (se conocen las distribuciones) se puede calcular la frontera óptima analíticamente; en el caso real solo hay una muestra, y la frontera estimada mejora al aumentar el número de datos. | H17: Media | I17: 27/09/2026 | J17: resumen_cap1_tema1.txt
A18: 1.3 | B18: 1. Fundamentos y preparación de datos | C18: Estructura de datos: instancias, atributos y clase | D18: 1 | E18: 🟢 Comprendido | F18: La tabla de datos (dataset) es la estructura fundamental: filas = instancias, columnas = atributos (más la clase, que es la variable de salida). Notación formal: X (atributos), y (clase). | G18: Practicar identificando instancias, atributos y clase en un dataset real como iris o penguins. | H18: Alta | I18: 27/09/2026 | J18: resumen_cap1_tema1.txt
A19: 1.3.a | B19: 1. Fundamentos y preparación de datos | C19: Instancia | D19: 2 | E19: 🟢 Comprendido | F19: Cada FILA de la tabla de datos (también llamada ejemplo, muestra, observación o punto). | H19: Alta | I19: 27/09/2026 | J19: resumen_cap1_tema1.txt
A20: 1.3.b | B20: 1. Fundamentos y preparación de datos | C20: Atributo / característica | D20: 2 | E20: 🟢 Comprendido | F20: Cada columna de la tabla excepto la clase (también llamada característica, feature, variable de entrada o predictora). | H20: Alta | I20: 27/09/2026 | J20: resumen_cap1_tema1.txt
A21: 1.3.c | B21: 1. Fundamentos y preparación de datos | C21: Clase / variable objetivo | D21: 2 | E21: 🟢 Comprendido | F21: La variable de salida usada en aprendizaje supervisado (también etiqueta, target, respuesta). Numérica en regresión, categórica en clasificación. | H21: Alta | I21: 27/09/2026 | J21: resumen_cap1_tema1.txt
A22: 1.3.d | B22: 1. Fundamentos y preparación de datos | C22: Notación formal X, y, eᵢ, xⱼ, xᵢⱼ | D22: 2 | E22: 🟡 Repasar | F22: X es la matriz de p atributos × n instancias; y es el vector de la clase; eᵢ es la instancia i; xⱼ es el atributo j; xᵢⱼ es el valor del atributo j para la instancia i. Fórmula/Cómo: X (n instancias × p atributos), y (vector de clase) | H22: Alta | I22: 27/09/2026 | J22: resumen_cap1_tema1.txt
A23: 1.3.e | B23: 1. Fundamentos y preparación de datos | C23: Parámetros vs. hiperparámetros | D23: 2 | E23: 🟢 Comprendido | F23: Los parámetros pertenecen al modelo y se ajustan durante el entrenamiento; los hiperparámetros pertenecen al algoritmo de aprendizaje, se fijan antes de entrenar y quedan constantes. | H23: Media | I23: 27/09/2026 | J23: resumen_cap1_tema1.txt
A24: 1.3.f | B24: 1. Fundamentos y preparación de datos | C24: Características de un conjunto de datos | D24: 2 | E24: 🟡 Repasar | F24: Al iniciar un proyecto se anota: número de instancias, número de atributos, tipo/dominio de cada uno, tipo y dominio de la clase, y cantidad de valores ausentes (ej. iris: 150 instancias, 4 atributos, 3 clases, 0 ausentes). | H24: Baja | I24: 27/09/2026 | J24: resumen_cap1_tema1.txt
A25: 1.4 | B25: 1. Fundamentos y preparación de datos | C25: Limpieza de datos — introducción | D25: 1 | E25: 🟢 Comprendido | F25: Tarea fundamental dentro de la fase de preparación de datos de CRISP-DM: elimina defectos y adapta los datos para que expongan sus patrones con la mayor nitidez posible antes del modelado. | G25: Repasar junto con las 4 técnicas concretas (normalización, outliers, imputación, selección) que desarrollan esta fase. | H25: Media | I25: 27/09/2026 | J25: resumen_cap1_tema1.txt
A26: 1.4.a | B26: 1. Fundamentos y preparación de datos | C26: Técnicas de fila, columna o matriz completa | D26: 2 | E26: 🟡 Repasar | F26: Según la parte de la tabla sobre la que actúan: de fila, de columna (ej. la normalización actúa sobre toda una columna) o de matriz completa. | H26: Baja | I26: 27/09/2026 | J26: resumen_cap1_tema1.txt
A27: 1.4.b | B27: 1. Fundamentos y preparación de datos | C27: Limpieza supervisada vs. no supervisada | D27: 2 | E27: 🟢 Comprendido | F27: Igual que el aprendizaje automático, las técnicas de limpieza pueden requerir o no la presencia de una clase. | H27: Baja | I27: 27/09/2026 | J27: resumen_cap1_tema1.txt
A28: 1.5 | B28: 1. Fundamentos y preparación de datos | C28: Normalización y estandarización | D28: 1 | E28: 🟢 Comprendido | F28: Dos técnicas para llevar los atributos numéricos a una escala común (centrar y escalar), evitando que un atributo con mayor escala domine artificialmente sobre otro de igual importancia real. Fórmula/Cómo: Normalización: x_N=(x-min)/(max-min); Estandarización: x_S=(x-media)/desviación | G28: Practicar aplicando MinMaxScaler y StandardScaler con fit en train y transform en test. | H28: Alta | I28: 27/09/2026 | J28: resumen_cap1_tema1.txt
A29: 1.5.a | B29: 1. Fundamentos y preparación de datos | C29: Normalización | D29: 2 | E29: 🟢 Comprendido | F29: Lleva los valores de un atributo al rango [0,1] mediante homotecia (resta del mínimo = centrado, división por el rango = escalado). Se aplica columna por columna. Fórmula/Cómo: x_ij^N = (x_ij - min(x_i)) / (max(x_i) - min(x_i)) | H29: Alta | I29: 27/09/2026 | J29: resumen_cap1_tema1.txt
A30: 1.5.b | B30: 1. Fundamentos y preparación de datos | C30: Estandarización | D30: 2 | E30: 🟢 Comprendido | F30: Transforma un atributo para que tenga media y desviación típica determinadas (centrado en la media). A diferencia de la normalización, no queda acotada a un rango fijo. Fórmula/Cómo: x_ij^S = (x_ij - media(x_i)) / desviación(x_i) | H30: Alta | I30: 27/09/2026 | J30: resumen_cap1_tema1.txt
A31: 1.5.c | B31: 1. Fundamentos y preparación de datos | C31: Cuándo usar cada técnica | D31: 2 | E31: 🟢 Comprendido | F31: Normalización cuando el algoritmo NO presupone una distribución de los datos; estandarización cuando el algoritmo SÍ presupone que los datos siguen una distribución normal. | H31: Media | I31: 27/09/2026 | J31: resumen_cap1_tema1.txt
A32: 1.5.d | B32: 1. Fundamentos y preparación de datos | C32: Evitar fuga de información (data leakage) | D32: 2 | E32: 🟢 Comprendido | F32: Al dividir en train/test hay que ajustar (fit) el normalizador/estandarizador SOLO con train, y aplicar (transform) esa misma transformación sobre test, sin reajustar sobre test. | H32: Alta | I32: 27/09/2026 | J32: resumen_cap1_tema1.txt
A33: 1.6 | B33: 1. Fundamentos y preparación de datos | C33: Detección de outliers | D33: 1 | E33: 🟢 Comprendido | F33: Identificar valores anómalos fuera de la distribución natural de los datos, que pueden reducir la eficacia de los modelos. El límite entre outlier y no-outlier suele ser difuso. | G33: Practicar EllipticEnvelope y el método boxplot sobre el dataset outliers.csv. | H33: Alta | I33: 27/09/2026 | J33: resumen_cap1_tema1.txt
A34: 1.6.a | B34: 1. Fundamentos y preparación de datos | C34: Envolvente elíptica (EllipticEnvelope) | D34: 2 | E34: 🟢 Comprendido | F34: Presupone datos con distribución normal; crea elipses alrededor de los puntos 'normales'. Cuanto mayor la elipse que engloba un punto, mayor su distancia y su probabilidad de ser outlier. Fórmula/Cómo: sklearn.covariance.EllipticEnvelope | H34: Alta | I34: 27/09/2026 | J34: resumen_cap1_tema1.txt
A35: 1.6.b | B35: 1. Fundamentos y preparación de datos | C35: Mediana e IQR como base del cálculo | D35: 2 | E35: 🟢 Comprendido | F35: Las elipses se centran y escalan respecto a la mediana y el rango intercuartílico (IQR), en vez de la media, porque la media se distorsiona con los propios outliers. Fórmula/Cómo: IQR = P75 - P25; umbral típico: mediana ± 1,5·IQR o ± 3·IQR | H35: Media | I35: 27/09/2026 | J35: resumen_cap1_tema1.txt
A36: 1.6.c | B36: 1. Fundamentos y preparación de datos | C36: Umbral por percentil vs. contamination fijo | D36: 2 | E36: 🟢 Comprendido | F36: El PDF usa decision_function() + scoreatpercentile(25) para fijar el umbral; el notebook usa predict() con contamination=0.25 fijo (misma clase, técnica distinta de fijar el umbral). | H36: Media | I36: 27/09/2026 | J36: resumen_cap1_tema1.txt
A37: 1.6.d | B37: 1. Fundamentos y preparación de datos | C37: Método boxplot / cajas y bigotes | D37: 2 | E37: 🔴 Débil | F37: Técnica solo del notebook: usa Q1, Q3, IQR y límites superior/inferior para marcar como outlier todo valor fuera de esos límites. Fórmula/Cómo: límite superior = P75+1.5·IQR; límite inferior = P25-1.5·IQR | H37: Media | I37: 27/09/2026 | J37: resumen_cap1_tema1.txt
A38: 1.6.e | B38: 1. Fundamentos y preparación de datos | C38: Otros detectores de outliers | D38: 2 | E38: 🔴 Débil | F38: Alternativas de sklearn con el mismo patrón fit/predict: IsolationForest, LocalOutlierFactor, OneClassSVM. | H38: Baja | I38: 27/09/2026 | J38: resumen_cap1_tema1.txt
A39: 1.7 | B39: 1. Fundamentos y preparación de datos | C39: Imputación de valores ausentes | D39: 1 | E39: 🔴 Débil | F39: Reemplazar valores ausentes (missing values / NaN) por valores estimados, en vez de eliminar instancias completas, para no perder información. | G39: Practicar SimpleImputer sobre datos reales (penguins.csv) con fit/transform. | H39: Alta | I39: 27/09/2026 | J39: resumen_cap1_tema1.txt
A40: 1.7.a | B40: 1. Fundamentos y preparación de datos | C40: Valores ausentes (missing values) | D40: 2 | E40: 🟢 Comprendido | F40: Huecos en los datos por información no recabada, no disponible o errónea y eliminada. En Python se representan con np.nan. | H40: Media | I40: 27/09/2026 | J40: resumen_cap1_tema1.txt
A41: 1.7.b | B41: 1. Fundamentos y preparación de datos | C41: Por qué no eliminar simplemente las filas | D41: 2 | E41: 🟢 Comprendido | F41: La mayoría de algoritmos de sklearn no toleran valores ausentes, pero eliminar todas las instancias afectadas puede suponer una pérdida importante de información; por eso se prefiere imputar. | H41: Media | I41: 27/09/2026 | J41: resumen_cap1_tema1.txt
A42: 1.7.c | B42: 1. Fundamentos y preparación de datos | C42: Imputación por media, mediana o moda | D42: 2 | E42: 🟢 Comprendido | F42: Técnica más simple: sustituir el valor ausente por la media/mediana del atributo si es numérico, o por la moda si es categórico. Existen técnicas más complejas basadas en modelos de aprendizaje supervisado. Fórmula/Cómo: sklearn.impute.SimpleImputer(strategy='mean'/'median'/'most_frequent') | H42: Alta | I42: 27/09/2026 | J42: resumen_cap1_tema1.txt
A43: 1.7.d | B43: 1. Fundamentos y preparación de datos | C43: Fit sobre train, transform sobre train y test | D43: 2 | E43: 🔴 Débil | F43: El imputador se ajusta (fit) sobre los datos de entrenamiento, y esa misma transformación se aplica (transform) tanto a train como a test, igual que en normalización/estandarización. | H43: Alta | I43: 27/09/2026 | J43: resumen_cap1_tema1.txt
A44: 1.8 | B44: 1. Fundamentos y preparación de datos | C44: Selección de atributos | D44: 1 | E44: 🟠 Parcial | F44: Subtarea de la reducción de dimensionalidad: elimina atributos poco útiles usando un algoritmo de evaluación que mide su 'bondad', ya sea de forma individual (univariante) o en conjunto (multivariante). | G44: Practicar VarianceThreshold, f_regression y mutual_info_regression sobre datos sintéticos y iris. | H44: Media | I44: 27/09/2026 | J44: resumen_cap1_tema1.txt
A45: 1.8.a | B45: 1. Fundamentos y preparación de datos | C45: Evaluación univariante vs. multivariante | D45: 2 | E45: 🟢 Comprendido | F45: Univariante evalúa cada atributo individualmente; multivariante evalúa conjuntos de atributos juntos. Un atributo puede tener baja bondad individual pero ser clave combinado con otros; multivariante es más costoso pero más preciso. | H45: Media | I45: 27/09/2026 | J45: resumen_cap1_tema1.txt
A46: 1.8.b | B46: 1. Fundamentos y preparación de datos | C46: Selección supervisada vs. no supervisada | D46: 2 | E46: 🟡 Repasar | F46: Supervisada: se analiza el atributo junto con la variable objetivo (puede estar definida solo para clasificación, solo regresión, o ambas). No supervisada: se analiza el atributo de forma independiente a la clase. | H46: Media | I46: 27/09/2026 | J46: resumen_cap1_tema1.txt
A47: 1.8.c | B47: 1. Fundamentos y preparación de datos | C47: Baja varianza (VarianceThreshold) | D47: 2 | E47: 🟢 Comprendido | F47: Técnica no supervisada: elimina atributos cuyos valores son prácticamente constantes, asumiendo que no aportan información predictiva. Fórmula/Cómo: sklearn.feature_selection.VarianceThreshold(threshold=...); S² = Σ(xi-x̄)²/(n-1) | H47: Alta | I47: 27/09/2026 | J47: resumen_cap1_tema1.txt
A48: 1.8.d | B48: 1. Fundamentos y preparación de datos | C48: F-test | D48: 2 | E48: 🟢 Comprendido | F48: Técnica supervisada univariante: mide el grado de dependencia LINEAL entre un atributo y la clase; útil para detectar correlación lineal. Fórmula/Cómo: sklearn.feature_selection.f_regression | H48: Alta | I48: 27/09/2026 | J48: resumen_cap1_tema1.txt
A49: 1.8.e | B49: 1. Fundamentos y preparación de datos | C49: Información mutua | D49: 2 | E49: 🟢 Comprendido | F49: Técnica supervisada univariante: mide cualquier tipo de dependencia estadística (lineal o no lineal) entre un atributo y la clase, pero necesita más instancias para ser fiable. Fórmula/Cómo: sklearn.feature_selection.mutual_info_regression | H49: Alta | I49: 27/09/2026 | J49: resumen_cap1_tema1.txt
A50: 2 | B50: 2. Validación de modelos y métricas | C50: VALIDACIÓN DE MODELOS Y MÉTRICAS DE EVALUACIÓN | D50: 0 | E50: 🟢 Comprendido | F50: Cómo separar datos en entrenamiento/test, evitar sobreajuste/subajuste, validar con hold-out/k-fold/validación anidada, y medir el desempeño con métricas de regresión (MAE/MSE/RMSE/MAPE/R2) y de clasificación (matriz de confusión, precisión, sensibilidad, F1). Imprescindible para evaluar cualquier modelo de los temas 4 y 5. | G50: Dominar k-fold y la matriz de confusión (con sus 4 métricas derivadas) antes de avanzar a los modelos de los temas 4 y 5. | H50: Alta | I50: 27/09/2026 | J50: resumen_cap2_tema2.txt
A51: 2.1 | B51: 2. Validación de modelos y métricas | C51: Introducción: entrenamiento, test, sobreajuste y subajuste | D51: 1 | E51: 🟢 Comprendido | F51: Desde el capítulo 2 se estudian 4 algoritmos (regresión lineal, KNN, regresión logística, árboles). Se separan los datos en entrenamiento (para aprender) y test (para evaluar sobre ejemplos nunca vistos); esa separación es la base de toda validación. | G51: Distinguir claramente overfitting de underfitting con un ejemplo propio antes de pasar a hold-out. | H51: Alta | I51: 27/09/2026 | J51: resumen_cap2_tema2.txt
A52: 2.1.a | B52: 2. Validación de modelos y métricas | C52: Conjunto de entrenamiento y conjunto de test | D52: 2 | E52: 🟢 Comprendido | F52: Entrenamiento = datos que usa el algoritmo para aprender el modelo. Test = datos nunca vistos en el entrenamiento, usados solo para evaluar. El test no debe contener ninguna instancia del entrenamiento. | H52: Alta | I52: 27/09/2026 | J52: resumen_cap2_tema2.txt
A53: 2.1.b | B53: 2. Validación de modelos y métricas | C53: Sobreajuste (overfitting) | D53: 2 | E53: 🟢 Comprendido | F53: El modelo 'memoriza' el entrenamiento: error de entrenamiento muy bajo pero error de generalización (test) alto. | H53: Alta | I53: 27/09/2026 | J53: resumen_cap2_tema2.txt
A54: 2.1.c | B54: 2. Validación de modelos y métricas | C54: Subajuste (underfitting) | D54: 2 | E54: 🟢 Comprendido | F54: El modelo aprende un concepto demasiado general: error de entrenamiento y de test altos y parecidos entre sí. | H54: Alta | I54: 27/09/2026 | J54: resumen_cap2_tema2.txt
A55: 2.1.d | B55: 2. Validación de modelos y métricas | C55: Compromiso sesgo-varianza (bias-variance tradeoff) | D55: 2 | E55: 🟢 Comprendido | F55: Alto sesgo = underfitting (ni ajusta el entrenamiento). Alta varianza = overfitting (ajusta muy bien entrenamiento pero falla en datos nuevos). El puntaje de entrenamiento siempre es mayor que el de validación; existe un punto de complejidad óptimo intermedio. | H55: Media | I55: 27/09/2026 | J55: resumen_cap2_tema2.txt
A56: 2.1.e | B56: 2. Validación de modelos y métricas | C56: Validación (definición general) y métricas base | D56: 2 | E56: 🟢 Comprendido | F56: Validación = proceso de dividir los datos en subconjuntos de entrenamiento y test para evaluar bien los algoritmos. Se introducen dos métricas base: MAE (regresión) y Exactitud/accuracy (clasificación). Fórmula/Cómo: MAE = (1/n)·Σ|y_i - ŷ_i| | Exactitud(%) = 100·(1/n)·Σ[y_i = ŷ_i] | H56: Media | I56: 27/09/2026 | J56: resumen_cap2_tema2.txt
A57: 2.2 | B57: 2. Validación de modelos y métricas | C57: Validación hold-out | D57: 1 | E57: 🟢 Comprendido | F57: Divide el dataset en dos partes (train/test) una sola vez, con un reparto típico 66/34 o 70/30. | G57: Reproducir el Programa 7 (iris + DummyClassifier) a mano para fijar train_test_split. | H57: Alta | I57: 27/09/2026 | J57: resumen_cap2_tema2.txt
A58: 2.2.a | B58: 2. Validación de modelos y métricas | C58: Hold-out no aleatorio | D58: 2 | E58: 🟢 Comprendido | F58: Se toma el primer X% de las muestras (respetando el orden) para entrenamiento y el resto para test. Útil cuando hay dependencia entre muestras, p. ej. series temporales. | H58: Media | I58: 27/09/2026 | J58: resumen_cap2_tema2.txt
A59: 2.2.b | B59: 2. Validación de modelos y métricas | C59: Hold-out aleatorio | D59: 2 | E59: 🟢 Comprendido | F59: Se reordenan aleatoriamente las muestras y luego se hace el corte train/test. Recomendable cuando no hay dependencias de orden. | H59: Media | I59: 27/09/2026 | J59: resumen_cap2_tema2.txt
A60: 2.2.c | B60: 2. Validación de modelos y métricas | C60: train_test_split (código real) | D60: 2 | E60: 🟢 Comprendido | F60: Función de sklearn que reparte X e y en train/test. test_size fija la proporción de test, random_state fija la semilla de aleatoriedad, shuffle=False conserva el orden original. Fórmula/Cómo: X_train, X_test, y_train, y_test = train_test_split(X, y, test_size=0.3, random_state=0) | H60: Alta | I60: 27/09/2026 | J60: resumen_cap2_tema2.txt
A61: 2.2.d | B61: 2. Validación de modelos y métricas | C61: Partición train/test fijada por el problema | D61: 2 | E61: 🟢 Comprendido | F61: A veces la partición viene ya dada (para comparar con resultados de otros trabajos); también se considera una forma de hold-out. | H61: Baja | I61: 27/09/2026 | J61: resumen_cap2_tema2.txt
A62: 2.3 | B62: 2. Validación de modelos y métricas | C62: Validación cruzada / K-fold | D62: 1 | E62: 🟢 Comprendido | F62: Corrige la baja representatividad del hold-out: parte los datos en K bolsas (folds) de igual tamaño y hace K validaciones hold-out, usando cada vez una bolsa distinta como test. | G62: Ejecutar mentalmente el ejemplo KFold(n_splits=3) sobre 10 elementos para ver por qué las bolsas no quedan exactamente iguales. | H62: Alta | I62: 27/09/2026 | J62: resumen_cap2_tema2.txt
A63: 2.3.a | B63: 2. Validación de modelos y métricas | C63: K bolsas (folds) | D63: 2 | E63: 🟢 Comprendido | F63: El dataset se divide en K subconjuntos de tamaño aprox. n/K. En cada una de las K iteraciones, una bolsa distinta hace de test y el resto de entrenamiento. Fórmula/Cómo: Ej: 150 ejemplos (iris), K=10 → cada bolsa tiene 15 ejemplos. | H63: Alta | I63: 27/09/2026 | J63: resumen_cap2_tema2.txt
A64: 2.3.b | B64: 2. Validación de modelos y métricas | C64: Leave-one-out | D64: 2 | E64: 🟢 Comprendido | F64: Leave-One-Out: es una validación cruzada donde se deja un solo dato para test y todos los demás se usan para entrenar. Luego se repite el proceso hasta que cada dato haya sido test una vez. | H64: Media | I64: 27/09/2026 | J64: resumen_cap2_tema2.txt
A65: 2.3.c | B65: 2. Validación de modelos y métricas | C65: Validación estratificada | D65: 2 | E65: 🟢 Comprendido | F65: Si defines, por ejemplo, 70% para train y 30% para test, la validación estratificada respeta esa división y además mantiene aproximadamente la misma proporción de cada clase dentro de ambos grupos. | H65: Media | I65: 27/09/2026 | J65: resumen_cap2_tema2.txt
A66: 2.3.d | B66: 2. Validación de modelos y métricas | C66: cross_val_score / KFold (código real) | D66: 2 | E66: ⚪ Pendiente | F66: cross_val_score() recibe el estimador, X, y, y el objeto cv (p. ej. KFold(n_splits=10)) y devuelve un array con K valores de exactitud, uno por bolsa, que se resumen con media y desviación típica. Fórmula/Cómo: evaluacion = cross_val_score(clf, X, y, cv=KFold(n_splits=10)) | H66: Alta | I66: 27/09/2026 | J66: resumen_cap2_tema2.txt
A67: 2.3.e | B67: 2. Validación de modelos y métricas | C67: Bootstrapping / out-of-bag (OOB) | D67: 2 | E67: ⚪ Pendiente | F67: Tercera forma de re-muestreo: se seleccionan instancias con reemplazo hasta un tamaño fijo para entrenar; las no elegidas pasan a test y se llaman 'out of bag'. Nunca hay instancias repetidas entre train y test. Fórmula/Cómo: boot = resample(data, replace=True, n_samples=N) | H67: Media | I67: 27/09/2026 | J67: resumen_cap2_tema2.txt
A68: 2.4 | B68: 2. Validación de modelos y métricas | C68: Ajuste de parámetros y validación anidada | D68: 1 | E68: ⚪ Pendiente | F68: Encontrar la mejor configuración de hiperparámetros de un algoritmo (hyperparameter tuning), sin usar nunca el test para esa búsqueda, para no perder la capacidad de medir generalización. | G68: Explicar con palabras propias por qué el test debe quedar aislado del ajuste antes de ver validación anidada. | H68: Alta | I68: 27/09/2026 | J68: resumen_cap2_tema2.txt
A69: 2.4.a | B69: 2. Validación de modelos y métricas | C69: Regla: el test nunca se usa para ajustar parámetros | D69: 2 | E69: ⚪ Pendiente | F69: El ajuste de parámetros nunca debe maximizar la bondad sobre el conjunto de test; el test debe permanecer aislado durante todo el entrenamiento y ajuste para evitar sobreajuste. | H69: Alta | I69: 27/09/2026 | J69: resumen_cap2_tema2.txt
A70: 2.4.b | B70: 2. Validación de modelos y métricas | C70: Test de validación (validation test) | D70: 2 | E70: ⚪ Pendiente | F70: Subconjunto extraído del propio entrenamiento, usado para comparar configuraciones de modelo sin tocar el test independiente. El modelo final se evalúa una sola vez con el test real. | H70: Alta | I70: 27/09/2026 | J70: resumen_cap2_tema2.txt
A71: 2.4.c | B71: 2. Validación de modelos y métricas | C71: Validación anidada (nested validation) | D71: 2 | E71: ⚪ Pendiente | F71: Combina dos niveles: validación externa (partición original train/test) y validación interna (CV dentro del propio train, usada para el ajuste de parámetros). Tras hallar los mejores parámetros, se reentrena con todo el train y se evalúa una vez en el test independiente. | H71: Alta | I71: 27/09/2026 | J71: resumen_cap2_tema2.txt
A72: 2.4.d | B72: 2. Validación de modelos y métricas | C72: Curvas de validación y de aprendizaje | D72: 2 | E72: ⚪ Pendiente | F72: La curva de validación muestra cómo cambian el puntaje de entrenamiento y de validación al variar un hiperparámetro (p. ej. grado del polinomio). La curva de aprendizaje muestra lo mismo al variar el tamaño del conjunto de entrenamiento, con el hiperparámetro fijo. Fórmula/Cómo: validation_curve(...); learning_curve(...) | H72: Media | I72: 27/09/2026 | J72: resumen_cap2_tema2.txt
A73: 2.5 | B73: 2. Validación de modelos y métricas | C73: Evaluación en regresión: MAE, MSE, RMSE, MAPE | D73: 1 | E73: ⚪ Pendiente | F73: Métricas para medir qué tan lejos quedan las predicciones numéricas de los valores reales. MAE y RMSE son absolutas (misma unidad que la clase); MAPE es relativa (porcentaje). | G73: Construir una tabla de variables comparando MAE/MSE/RMSE/MAPE antes de memorizar fórmulas sueltas. | H73: Alta | I73: 27/09/2026 | J73: resumen_cap2_tema2.txt
A74: 2.5.a | B74: 2. Validación de modelos y métricas | C74: MAE (error absoluto medio) | D74: 2 | E74: ⚪ Pendiente | F74: Promedio de las diferencias absolutas entre predicción y valor real. Métrica absoluta: misma unidad que la variable de clase. Fórmula/Cómo: MAE = (1/n)·Σ|y_i - ŷ_i| | H74: Alta | I74: 27/09/2026 | J74: resumen_cap2_tema2.txt
A75: 2.5.b | B75: 2. Validación de modelos y métricas | C75: MSE (error cuadrático medio) | D75: 2 | E75: ⚪ Pendiente | F75: Promedio de las diferencias al cuadrado entre predicción y real; es RMSE sin la raíz. Fórmula/Cómo: MSE = (1/m)·Σ(ŷ_i - y_i)^2 | H75: Media | I75: 27/09/2026 | J75: resumen_cap2_tema2.txt
A76: 2.5.c | B76: 2. Validación de modelos y métricas | C76: RMSE (raíz del error cuadrático medio) | D76: 2 | E76: ⚪ Pendiente | F76: Como MAE pero elevando al cuadrado antes de promediar: los errores grandes pesan mucho más que en MAE. Fórmula/Cómo: RMSE = sqrt((1/n)·Σ(y_i - ŷ_i)^2) | H76: Alta | I76: 27/09/2026 | J76: resumen_cap2_tema2.txt
A77: 2.5.d | B77: 2. Validación de modelos y métricas | C77: MAPE (error porcentual absoluto medio) | D77: 2 | E77: ⚪ Pendiente | F77: Mide el error en porcentaje relativo al valor real, útil para comparar errores entre escalas distintas. Fórmula/Cómo: MAPE(%) = 100·(1/n)·Σ|y_i - ŷ_i|/y_i | H77: Media | I77: 27/09/2026 | J77: resumen_cap2_tema2.txt
A78: 2.5.e | B78: 2. Validación de modelos y métricas | C78: make_scorer y greater_is_better | D78: 2 | E78: ⚪ Pendiente | F78: sklearn asume por defecto que 'mayor valor = mejor'; como RMSE/MAPE son errores (menor = mejor), hay que pasar greater_is_better=False al construir la métrica con make_scorer(). cross_validate() permite evaluar varias métricas a la vez. Fórmula/Cómo: make_scorer(func, greater_is_better=False) | H78: Media | I78: 27/09/2026 | J78: resumen_cap2_tema2.txt
A79: 2.6 | B79: 2. Validación de modelos y métricas | C79: Evaluación en clasificación: matriz de confusión, precisión, sensibilidad, F1, accuracy | D79: 1 | E79: ⚪ Pendiente | F79: En clasificación solo importa acierto/fallo de la clase (no un grado de error como en regresión). La matriz de confusión es la base de todas las demás métricas. | G79: Practicar leyendo una matriz de confusión 2x2 y derivando TP/TN/FP/FN antes de calcular precisión/recall/F1. | H79: Alta | I79: 27/09/2026 | J79: resumen_cap2_tema2.txt
A80: 2.6.a | B80: 2. Validación de modelos y métricas | C80: Matriz de confusión | D80: 2 | E80: ⚪ Pendiente | F80: Matriz cuadrada de orden = número de clases; la celda P_i,j cuenta las predicciones cuya clase real es Ci y la predicha es Cj. Los aciertos son la suma de la diagonal. Fórmula/Cómo: Aciertos = Σ P_i,i ; Fallos = n − Σ P_i,i | H80: Alta | I80: 27/09/2026 | J80: resumen_cap2_tema2.txt
A81: 2.6.b | B81: 2. Validación de modelos y métricas | C81: TP / TN / FP / FN (caso binario) | D81: 2 | E81: ⚪ Pendiente | F81: TP: modelo dice 'sí' y la realidad es 'sí'. TN: dice 'no' y es 'no'. FP: dice 'sí' pero es 'no'. FN: dice 'no' pero es 'sí'. Base de precisión, sensibilidad y F1. | H81: Alta | I81: 27/09/2026 | J81: resumen_cap2_tema2.txt
A82: 2.6.c | B82: 2. Validación de modelos y métricas | C82: Exactitud (accuracy) | D82: 2 | E82: ⚪ Pendiente | F82: Proporción de aciertos sobre el total de predicciones. Puede ser engañosa en datasets desbalanceados. Fórmula/Cómo: Exactitud = 100·(TP+TN)/(TP+TN+FP+FN) ; caso general: 100·(Σ P_i,i)/n | H82: Alta | I82: 27/09/2026 | J82: resumen_cap2_tema2.txt
A83: 2.6.d | B83: 2. Validación de modelos y métricas | C83: Precisión | D83: 2 | E83: ⚪ Pendiente | F83: De todo lo que el modelo predijo como positivo, qué proporción acertó. Mide cuánto confiar cuando el modelo dice 'sí'. Fórmula/Cómo: Precisión = TP / (TP + FP) | H83: Alta | I83: 27/09/2026 | J83: resumen_cap2_tema2.txt
A84: 2.6.e | B84: 2. Validación de modelos y métricas | C84: Sensibilidad / Recall / Exhaustividad | D84: 2 | E84: ⚪ Pendiente | F84: De todos los casos realmente positivos, qué proporción detectó el modelo. Mide si se está dejando escapar positivos reales (falsos negativos). Fórmula/Cómo: Sensibilidad = TP / (TP + FN) | H84: Alta | I84: 27/09/2026 | J84: resumen_cap2_tema2.txt
A85: 2.6.f | B85: 2. Validación de modelos y métricas | C85: F1-score | D85: 2 | E85: ⚪ Pendiente | F85: Media armónica entre precisión y sensibilidad; resume ambas en un solo número cuando mejorar una empeora la otra. Fórmula/Cómo: F1 = 2·(Precisión·Sensibilidad)/(Precisión+Sensibilidad) | H85: Alta | I85: 27/09/2026 | J85: resumen_cap2_tema2.txt
A86: 2.6.g | B86: 2. Validación de modelos y métricas | C86: Datos no balanceados: por qué accuracy engaña | D86: 2 | E86: ⚪ Pendiente | F86: En un dataset con ratio 9:1, un clasificador que siempre predice la clase mayoritaria obtiene más del 80% de exactitud sin haber aprendido nada; por eso se necesitan precisión/recall/F1. | H86: Media | I86: 27/09/2026 | J86: resumen_cap2_tema2.txt
A87: 3 | B87: 3. Extracción de características | C87: EXTRACCIÓN DE CARACTERÍSTICAS (VARIABLES E IMÁGENES) | D87: 0 | E87: ⚪ Pendiente | F87: Análisis descriptivo de variables cualitativas/cuantitativas y, sobre todo, procesamiento de imágenes: transformaciones de intensidad, espacios de color, transformaciones geométricas, segmentación y descriptores de forma y de textura (GLCM, SIFT, SURF, HOG, LBP). El manual PDF del curso NO cubre este tema: la teoría real vive solo en el PPTX del profesor. | G87: Empezar por variables cuantitativas y 'la imagen como dato' antes de los descriptores de forma y textura. | H87: Alta | I87: 27/09/2026 | J87: resumen_tema3.txt + Tema 3 - Extracción de características.pptx
A88: 3.1 | B88: 3. Extracción de características | C88: Conceptos básicos y variable estadística | D88: 1 | E88: ⚪ Pendiente | F88: Base de toda estadística descriptiva: distinguir población (todo lo que se quiere estudiar) de muestra (subconjunto representativo) y entender que una variable es el valor que toma cada instancia para una característica concreta. | G88: Practicar identificando población/muestra/variable en ejemplos propios antes de pasar a variables cualitativas y cuantitativas. | H88: Media | I88: 27/09/2026 | J88: Tema 3 - Extracción de características.pptx (diap. 3-6)
A89: 3.1.a | B89: 3. Extracción de características | C89: Población | D89: 2 | E89: ⚪ Pendiente | F89: Conjunto de ítems (instancias, sujetos, filas) que se desea estudiar o analizar. Ej: todos los lotes de un producto fabricado en masa. | H89: Baja | I89: 27/09/2026 | J89: pptx diap. 3
A90: 3.1.b | B90: 3. Extracción de características | C90: Muestra y muestreo representativo | D90: 2 | E90: ⚪ Pendiente | F90: Subconjunto de la población. Debe ser representativa (mediante muestreo aleatorio) para poder generalizar conclusiones a toda la población; un muestreo mal balanceado (ej. por edad o sexo) produce conclusiones erróneas. | H90: Media | I90: 27/09/2026 | J90: pptx diap. 3-4
A91: 3.1.c | B91: 3. Extracción de características | C91: Inferencia estadística | D91: 2 | E91: ⚪ Pendiente | F91: Proceso de razonamiento que permite obtener conclusiones sobre la población (con un margen de error conocido) a partir del análisis de la muestra. | H91: Baja | I91: 27/09/2026 | J91: pptx diap. 3
A92: 3.1.d | B92: 3. Extracción de características | C92: Variable estadística | D92: 2 | E92: ⚪ Pendiente | F92: Cualidad de los individuos de una población; es el valor que toma una instancia para una característica (columna/atributo) determinada, y puede variar entre ítems o en el tiempo. | H92: Media | I92: 27/09/2026 | J92: pptx diap. 5
A93: 3.2 | B93: 3. Extracción de características | C93: Análisis de variables cualitativas | D93: 1 | E93: ⚪ Pendiente | F93: Tratamiento de variables categóricas (ej. nivel de estudios) mediante conteo de frecuencias por categoría y su representación gráfica, para resumir la muestra sin tener que recorrerla entera. | G93: Practicar construyendo una tabla de frecuencias y su gráfico de barras/sectores con una variable categórica propia. | H93: Media | I93: 27/09/2026 | J93: pptx diap. 7-8 + notebook var_cualitativas
A94: 3.2.a | B94: 3. Extracción de características | C94: Tablas de frecuencia | D94: 2 | E94: ⚪ Pendiente | F94: Resumen del número de apariciones (frecuencia absoluta) de cada categoría en la muestra, para analizarla de forma organizada. Fórmula/Cómo: np.unique(datos, return_counts=True) | H94: Media | I94: 27/09/2026 | J94: pptx diap. 7 + notebook
A95: 3.2.b | B95: 3. Extracción de características | C95: Representación gráfica (barras y sectores) | D95: 2 | E95: ⚪ Pendiente | F95: Visualización de las frecuencias por categoría: diagrama de barras (altura = frecuencia) o diagrama de sectores/pie (porcentaje del total). Fórmula/Cómo: plt.bar(categorias, frecuencia) / plt.pie(frecuencia, labels=categorias, autopct=...) | H95: Baja | I95: 27/09/2026 | J95: notebook var_cualitativas
A96: 3.3 | B96: 3. Extracción de características | C96: Análisis de variables cuantitativas | D96: 1 | E96: ⚪ Pendiente | F96: Conjunto de medidas numéricas que describen una muestra de datos numéricos desde cuatro ángulos: dónde se centra, cómo se ordena, cuánto se dispersa y cómo se distribuye. Son símbolos parecidos que conviene separar uno a uno para no confundirlos. | G96: Calcular las 4 familias de medidas sobre un mismo vector de datos y comparar qué aporta cada una. | H96: Alta | I96: 27/09/2026 | J96: pptx diap. 9-10 + notebook var_cuantitativas
A97: 3.3.a | B97: 3. Extracción de características | C97: Medidas de tendencia central: media, mediana, moda | D97: 2 | E97: ⚪ Pendiente | F97: Tres formas distintas de resumir 'el centro' de los datos: media = promedio aritmético, mediana = valor central al ordenar, moda = valor más frecuente. Fórmula/Cómo: media = np.mean(X); mediana = np.median(X); moda = stats.mode(X) | H97: Alta | I97: 27/09/2026 | J97: pptx diap. 9 + notebook
A98: 3.3.b | B98: 3. Extracción de características | C98: Medidas de posición: cuartiles, RIC y límites de outliers | D98: 2 | E98: ⚪ Pendiente | F98: Los cuartiles dividen los datos ordenados en 4 partes; el rango intercuartílico (RIC=Q3-Q1) mide la dispersión del 50% central, y con la regla 1.5·RIC se marcan los límites fuera de los cuales un valor se considera outlier. Fórmula/Cómo: RIC = Q3 - Q1; lim_inf = Q1 - 1.5·RIC; lim_sup = Q3 + 1.5·RIC | H98: Alta | I98: 27/09/2026 | J98: notebook var_cuantitativas
A99: 3.3.c | B99: 3. Extracción de características | C99: Medidas de dispersión: varianza y desviación típica | D99: 2 | E99: ⚪ Pendiente | F99: Cuánto se alejan en promedio los datos de la media. La desviación típica es la raíz de la varianza y se expresa en las mismas unidades que el dato original. Fórmula/Cómo: desvest = np.std(X); varianza = desvest**2 | H99: Alta | I99: 27/09/2026 | J99: pptx diap. 10 + notebook
A100: 3.3.d | B100: 3. Extracción de características | C100: Medidas de distribución: asimetría y curtosis | D100: 2 | E100: ⚪ Pendiente | F100: La asimetría (skewness) indica si la distribución se inclina más hacia un lado de la media; la curtosis indica qué tan puntiaguda o achatada es respecto a la normal (curtosis>0 leptocúrtica, <0 platicúrtica, =0 mesocúrtica). Fórmula/Cómo: asimetria = stats.skew(X); curtosis = stats.kurtosis(X, fisher=True) | H100: Media | I100: 27/09/2026 | J100: notebook var_cuantitativas
...
