Workbook

Sheet Resumen
A1: APRENDIZAJE SUPERVISADO — SEGUIMIENTO DE ESTUDIO | J1: TODOS LOS TEMAS DEL CURSO — 34 temas (nivel 0 y 1, los 5 bloques)
J2: Código | K2: Bloque | L2: Tema | M2: Estado | N2: Prioridad
A3: Este libro conserva tus estados de estudio (columna E de «Mapa de estudio»: no se modificaron). La columna F da la explicación sencilla y las columnas K a O reúnen el conocimiento del curso: definición precisa y fórmula, ejemplo o código, errores comunes, una pregunta de comprobación y la fuente exacta. El mismo contenido, con escenas y profundización, está en la carpeta «2_Prompt_para_video» (archivo único PROMPT_VIDEO_APRENDIZAJE_SUPERVISADO.md) para que otra IA te lo explique en video. Comprendido aún no significa firme. | J3: ='Mapa de estudio'!A2 | K3: =J3 | L3: ='Mapa de estudio'!C2 | M3: ='Mapa de estudio'!E2 | N3: ='Mapa de estudio'!H2
J4: ='Mapa de estudio'!A3 | K4: =J4 | L4: ='Mapa de estudio'!C3 | M4: ='Mapa de estudio'!E3 | N4: ='Mapa de estudio'!H3
A5: Total conceptos | C5: Firmes | E5: Pendientes | G5: Débiles | J5: ='Mapa de estudio'!A11 | K5: =J5 | L5: ='Mapa de estudio'!C11 | M5: ='Mapa de estudio'!E11 | N5: ='Mapa de estudio'!H11
A6: =COUNTA('Mapa de estudio'!$A$2:$A$186) | C6: =COUNTIF('Mapa de estudio'!$E$2:$E$186,"🟢 Firme") | E6: =COUNTIF('Mapa de estudio'!$E$2:$E$186,"⚪ Pendiente") | G6: =COUNTIF('Mapa de estudio'!$E$2:$E$186,"🔴 Débil") | J6: ='Mapa de estudio'!A18 | K6: =J6 | L6: ='Mapa de estudio'!C18 | M6: ='Mapa de estudio'!E18 | N6: ='Mapa de estudio'!H18
J7: ='Mapa de estudio'!A25 | K7: =J7 | L7: ='Mapa de estudio'!C25 | M7: ='Mapa de estudio'!E25 | N7: ='Mapa de estudio'!H25
J8: ='Mapa de estudio'!A28 | K8: =J8 | L8: ='Mapa de estudio'!C28 | M8: ='Mapa de estudio'!E28 | N8: ='Mapa de estudio'!H28
A9: Estado | B9: Cantidad | D9: TEMA EN CURSO — TEMA 1: FUNDAMENTOS Y PREPARACIÓN DE DATOS (ver los 5 temas completos en J:N) | J9: ='Mapa de estudio'!A33 | K9: =J9 | L9: ='Mapa de estudio'!C33 | M9: ='Mapa de estudio'!E33 | N9: ='Mapa de estudio'!H33
A10: 🟢 Firme | B10: =COUNTIF('Mapa de estudio'!$E$2:$E$186,A10) | D10: Concepto | E10: Estado | F10: Idea clave | G10: Siguiente | H10: Prioridad | J10: ='Mapa de estudio'!A39 | K10: =J10 | L10: ='Mapa de estudio'!C39 | M10: ='Mapa de estudio'!E39 | N10: ='Mapa de estudio'!H39
A11: 🟢 Comprendido | B11: =COUNTIF('Mapa de estudio'!$E$2:$E$186,A11) | D11: ='Mapa de estudio'!C3 | E11: ='Mapa de estudio'!E3 | F11: ='Mapa de estudio'!F3&"" | G11: ='Mapa de estudio'!G3&"" | H11: ='Mapa de estudio'!H3 | J11: ='Mapa de estudio'!A44 | K11: =J11 | L11: ='Mapa de estudio'!C44 | M11: ='Mapa de estudio'!E44 | N11: ='Mapa de estudio'!H44
A12: 🟡 Repasar | B12: =COUNTIF('Mapa de estudio'!$E$2:$E$186,A12) | D12: ='Mapa de estudio'!C11 | E12: ='Mapa de estudio'!E11 | F12: ='Mapa de estudio'!F11&"" | G12: ='Mapa de estudio'!G11&"" | H12: ='Mapa de estudio'!H11 | J12: ='Mapa de estudio'!A50 | K12: =J12 | L12: ='Mapa de estudio'!C50 | M12: ='Mapa de estudio'!E50 | N12: ='Mapa de estudio'!H50
A13: 🟠 Iniciado | B13: =COUNTIF('Mapa de estudio'!$E$2:$E$186,A13) | D13: ='Mapa de estudio'!C18 | E13: ='Mapa de estudio'!E18 | F13: ='Mapa de estudio'!F18&"" | G13: ='Mapa de estudio'!G18&"" | H13: ='Mapa de estudio'!H18 | J13: ='Mapa de estudio'!A51 | K13: =J13 | L13: ='Mapa de estudio'!C51 | M13: ='Mapa de estudio'!E51 | N13: ='Mapa de estudio'!H51
A14: 🟠 Parcial | B14: =COUNTIF('Mapa de estudio'!$E$2:$E$186,A14) | D14: ='Mapa de estudio'!C25 | E14: ='Mapa de estudio'!E25 | F14: ='Mapa de estudio'!F25&"" | G14: ='Mapa de estudio'!G25&"" | H14: ='Mapa de estudio'!H25 | J14: ='Mapa de estudio'!A57 | K14: =J14 | L14: ='Mapa de estudio'!C57 | M14: ='Mapa de estudio'!E57 | N14: ='Mapa de estudio'!H57
A15: ⚪ Pendiente | B15: =COUNTIF('Mapa de estudio'!$E$2:$E$186,A15) | D15: ='Mapa de estudio'!C28 | E15: ='Mapa de estudio'!E28 | F15: ='Mapa de estudio'!F28&"" | G15: ='Mapa de estudio'!G28&"" | H15: ='Mapa de estudio'!H28 | J15: ='Mapa de estudio'!A62 | K15: =J15 | L15: ='Mapa de estudio'!C62 | M15: ='Mapa de estudio'!E62 | N15: ='Mapa de estudio'!H62
A16: 🔴 Débil | B16: =COUNTIF('Mapa de estudio'!$E$2:$E$186,A16) | D16: ='Mapa de estudio'!C33 | E16: ='Mapa de estudio'!E33 | F16: ='Mapa de estudio'!F33&"" | G16: ='Mapa de estudio'!G33&"" | H16: ='Mapa de estudio'!H33 | J16: ='Mapa de estudio'!A68 | K16: =J16 | L16: ='Mapa de estudio'!C68 | M16: ='Mapa de estudio'!E68 | N16: ='Mapa de estudio'!H68
D17: ='Mapa de estudio'!C39 | E17: ='Mapa de estudio'!E39 | F17: ='Mapa de estudio'!F39&"" | G17: ='Mapa de estudio'!G39&"" | H17: ='Mapa de estudio'!H39 | J17: ='Mapa de estudio'!A73 | K17: =J17 | L17: ='Mapa de estudio'!C73 | M17: ='Mapa de estudio'!E73 | N17: ='Mapa de estudio'!H73
D18: ='Mapa de estudio'!C44 | E18: ='Mapa de estudio'!E44 | F18: ='Mapa de estudio'!F44&"" | G18: ='Mapa de estudio'!G44&"" | H18: ='Mapa de estudio'!H44 | J18: ='Mapa de estudio'!A79 | K18: =J18 | L18: ='Mapa de estudio'!C79 | M18: ='Mapa de estudio'!E79 | N18: ='Mapa de estudio'!H79
J19: ='Mapa de estudio'!A87 | K19: =J19 | L19: ='Mapa de estudio'!C87 | M19: ='Mapa de estudio'!E87 | N19: ='Mapa de estudio'!H87
A20: Criterio de avance: «Firme» exige resolver un caso nuevo. «Comprendido» significa que puedes explicarlo, pero todavía falta comprobar su aplicación. Los contadores y porcentajes de firmeza usan solo el estado «Firme». | J20: ='Mapa de estudio'!A88 | K20: =J20 | L20: ='Mapa de estudio'!C88 | M20: ='Mapa de estudio'!E88 | N20: ='Mapa de estudio'!H88
J21: ='Mapa de estudio'!A93 | K21: =J21 | L21: ='Mapa de estudio'!C93 | M21: ='Mapa de estudio'!E93 | N21: ='Mapa de estudio'!H93
A22: PROGRESO POR BLOQUE — LOS 5 TEMAS DEL CURSO | J22: ='Mapa de estudio'!A96 | K22: =J22 | L22: ='Mapa de estudio'!C96 | M22: ='Mapa de estudio'!E96 | N22: ='Mapa de estudio'!H96
A23: Bloque | B23: Total | C23: 🟢 Firme | D23: 🟠 En progreso | E23: 🟡 Repasar | F23: ⚪ Pendiente | G23: 🔴 Débil | H23: % Firme | J23: ='Mapa de estudio'!A101 | K23: =J23 | L23: ='Mapa de estudio'!C101 | M23: ='Mapa de estudio'!E101 | N23: ='Mapa de estudio'!H101
A24: 1. Fundamentos y preparación de datos | B24: =COUNTIF('Mapa de estudio'!$B$2:$B$186,$A24) | C24: =COUNTIFS('Mapa de estudio'!$B$2:$B$186,$A24,'Mapa de estudio'!$E$2:$E$186,"🟢 Firme") | D24: =COUNTIFS('Mapa de estudio'!$B$2:$B$186,$A24,'Mapa de estudio'!$E$2:$E$186,"🟢 Comprendido")+COUNTIFS('Mapa de estudio'!$B$2:$B$186,$A24,'Mapa de estudio'!$E$2:$E$186,"🟠 Iniciado")+COUNTIFS('Mapa de estudio'!$B$2:$B$186,$A24,'Mapa de estudio'!$E$2:$E$186,"🟠 Parcial") | E24: =COUNTIFS('Mapa de estudio'!$B$2:$B$186,$A24,'Mapa de estudio'!$E$2:$E$186,"🟡 Repasar") | F24: =COUNTIFS('Mapa de estudio'!$B$2:$B$186,$A24,'Mapa de estudio'!$E$2:$E$186,"⚪ Pendiente") | G24: =COUNTIFS('Mapa de estudio'!$B$2:$B$186,$A24,'Mapa de estudio'!$E$2:$E$186,"🔴 Débil") | H24: =IF(B24=0,0,C24/B24) | J24: ='Mapa de estudio'!A102 | K24: =J24 | L24: ='Mapa de estudio'!C102 | M24: ='Mapa de estudio'!E102 | N24: ='Mapa de estudio'!H102
A25: 2. Validación de modelos y métricas | B25: =COUNTIF('Mapa de estudio'!$B$2:$B$186,$A25) | C25: =COUNTIFS('Mapa de estudio'!$B$2:$B$186,$A25,'Mapa de estudio'!$E$2:$E$186,"🟢 Firme") | D25: =COUNTIFS('Mapa de estudio'!$B$2:$B$186,$A25,'Mapa de estudio'!$E$2:$E$186,"🟢 Comprendido")+COUNTIFS('Mapa de estudio'!$B$2:$B$186,$A25,'Mapa de estudio'!$E$2:$E$186,"🟠 Iniciado")+COUNTIFS('Mapa de estudio'!$B$2:$B$186,$A25,'Mapa de estudio'!$E$2:$E$186,"🟠 Parcial") | E25: =COUNTIFS('Mapa de estudio'!$B$2:$B$186,$A25,'Mapa de estudio'!$E$2:$E$186,"🟡 Repasar") | F25: =COUNTIFS('Mapa de estudio'!$B$2:$B$186,$A25,'Mapa de estudio'!$E$2:$E$186,"⚪ Pendiente") | G25: =COUNTIFS('Mapa de estudio'!$B$2:$B$186,$A25,'Mapa de estudio'!$E$2:$E$186,"🔴 Débil") | H25: =IF(B25=0,0,C25/B25) | J25: ='Mapa de estudio'!A106 | K25: =J25 | L25: ='Mapa de estudio'!C106 | M25: ='Mapa de estudio'!E106 | N25: ='Mapa de estudio'!H106
A26: 3. Extracción de características | B26: =COUNTIF('Mapa de estudio'!$B$2:$B$186,$A26) | C26: =COUNTIFS('Mapa de estudio'!$B$2:$B$186,$A26,'Mapa de estudio'!$E$2:$E$186,"🟢 Firme") | D26: =COUNTIFS('Mapa de estudio'!$B$2:$B$186,$A26,'Mapa de estudio'!$E$2:$E$186,"🟢 Comprendido")+COUNTIFS('Mapa de estudio'!$B$2:$B$186,$A26,'Mapa de estudio'!$E$2:$E$186,"🟠 Iniciado")+COUNTIFS('Mapa de estudio'!$B$2:$B$186,$A26,'Mapa de estudio'!$E$2:$E$186,"🟠 Parcial") | E26: =COUNTIFS('Mapa de estudio'!$B$2:$B$186,$A26,'Mapa de estudio'!$E$2:$E$186,"🟡 Repasar") | F26: =COUNTIFS('Mapa de estudio'!$B$2:$B$186,$A26,'Mapa de estudio'!$E$2:$E$186,"⚪ Pendiente") | G26: =COUNTIFS('Mapa de estudio'!$B$2:$B$186,$A26,'Mapa de estudio'!$E$2:$E$186,"🔴 Débil") | H26: =IF(B26=0,0,C26/B26) | J26: ='Mapa de estudio'!A111 | K26: =J26 | L26: ='Mapa de estudio'!C111 | M26: ='Mapa de estudio'!E111 | N26: ='Mapa de estudio'!H111
A27: 4. Modelos de regresión | B27: =COUNTIF('Mapa de estudio'!$B$2:$B$186,$A27) | C27: =COUNTIFS('Mapa de estudio'!$B$2:$B$186,$A27,'Mapa de estudio'!$E$2:$E$186,"🟢 Firme") | D27: =COUNTIFS('Mapa de estudio'!$B$2:$B$186,$A27,'Mapa de estudio'!$E$2:$E$186,"🟢 Comprendido")+COUNTIFS('Mapa de estudio'!$B$2:$B$186,$A27,'Mapa de estudio'!$E$2:$E$186,"🟠 Iniciado")+COUNTIFS('Mapa de estudio'!$B$2:$B$186,$A27,'Mapa de estudio'!$E$2:$E$186,"🟠 Parcial") | E27: =COUNTIFS('Mapa de estudio'!$B$2:$B$186,$A27,'Mapa de estudio'!$E$2:$E$186,"🟡 Repasar") | F27: =COUNTIFS('Mapa de estudio'!$B$2:$B$186,$A27,'Mapa de estudio'!$E$2:$E$186,"⚪ Pendiente") | G27: =COUNTIFS('Mapa de estudio'!$B$2:$B$186,$A27,'Mapa de estudio'!$E$2:$E$186,"🔴 Débil") | H27: =IF(B27=0,0,C27/B27) | J27: ='Mapa de estudio'!A116 | K27: =J27 | L27: ='Mapa de estudio'!C116 | M27: ='Mapa de estudio'!E116 | N27: ='Mapa de estudio'!H116
A28: 5. Modelos de clasificación | B28: =COUNTIF('Mapa de estudio'!$B$2:$B$186,$A28) | C28: =COUNTIFS('Mapa de estudio'!$B$2:$B$186,$A28,'Mapa de estudio'!$E$2:$E$186,"🟢 Firme") | D28: =COUNTIFS('Mapa de estudio'!$B$2:$B$186,$A28,'Mapa de estudio'!$E$2:$E$186,"🟢 Comprendido")+COUNTIFS('Mapa de estudio'!$B$2:$B$186,$A28,'Mapa de estudio'!$E$2:$E$186,"🟠 Iniciado")+COUNTIFS('Mapa de estudio'!$B$2:$B$186,$A28,'Mapa de estudio'!$E$2:$E$186,"🟠 Parcial") | E28: =COUNTIFS('Mapa de estudio'!$B$2:$B$186,$A28,'Mapa de estudio'!$E$2:$E$186,"🟡 Repasar") | F28: =COUNTIFS('Mapa de estudio'!$B$2:$B$186,$A28,'Mapa de estudio'!$E$2:$E$186,"⚪ Pendiente") | G28: =COUNTIFS('Mapa de estudio'!$B$2:$B$186,$A28,'Mapa de estudio'!$E$2:$E$186,"🔴 Débil") | H28: =IF(B28=0,0,C28/B28) | J28: ='Mapa de estudio'!A120 | K28: =J28 | L28: ='Mapa de estudio'!C120 | M28: ='Mapa de estudio'!E120 | N28: ='Mapa de estudio'!H120
A29: TOTAL CURSO | B29: =SUM(B24:B28) | C29: =SUM(C24:C28) | D29: =SUM(D24:D28) | E29: =SUM(E24:E28) | F29: =SUM(F24:F28) | G29: =SUM(G24:G28) | H29: =IF(B29=0,0,C29/B29) | J29: ='Mapa de estudio'!A126 | K29: =J29 | L29: ='Mapa de estudio'!C126 | M29: ='Mapa de estudio'!E126 | N29: ='Mapa de estudio'!H126
A30: Orden pedagógico del curso: Bloque 1 → 2 → 3 → 4 → 5 (respeta el orden real de las carpetas tema1-tema5 del repositorio). El bloque 3 (Extracción de características) va antes de los modelos de regresión/clasificación porque construye las variables/features que luego usan los temas 4 y 5. Ninguno está iniciado todavía. | J30: ='Mapa de estudio'!A127 | K30: =J30 | L30: ='Mapa de estudio'!C127 | M30: ='Mapa de estudio'!E127 | N30: ='Mapa de estudio'!H127
J31: ='Mapa de estudio'!A138 | K31: =J31 | L31: ='Mapa de estudio'!C138 | M31: ='Mapa de estudio'!E138 | N31: ='Mapa de estudio'!H138
J32: ='Mapa de estudio'!A142 | K32: =J32 | L32: ='Mapa de estudio'!C142 | M32: ='Mapa de estudio'!E142 | N32: ='Mapa de estudio'!H142
J33: ='Mapa de estudio'!A153 | K33: =J33 | L33: ='Mapa de estudio'!C153 | M33: ='Mapa de estudio'!E153 | N33: ='Mapa de estudio'!H153
J34: ='Mapa de estudio'!A154 | K34: =J34 | L34: ='Mapa de estudio'!C154 | M34: ='Mapa de estudio'!E154 | N34: ='Mapa de estudio'!H154
J35: ='Mapa de estudio'!A168 | K35: =J35 | L35: ='Mapa de estudio'!C168 | M35: ='Mapa de estudio'!E168 | N35: ='Mapa de estudio'!H168
J36: ='Mapa de estudio'!A183 | K36: =J36 | L36: ='Mapa de estudio'!C183 | M36: ='Mapa de estudio'!E183 | N36: ='Mapa de estudio'!H183

Sheet Mapa de estudio
A1: Código | B1: Bloque | C1: Tema / concepto | D1: Nivel | E1: Estado | F1: Explicación sencilla | G1: Siguiente aplicación | H1: Prioridad | I1: Actualizado | J1: Fuente | K1: Definición precisa y fórmula | L1: Ejemplo o código | M1: Ojo: error común o límite | N1: Pregunta de comprobación (una sola) | O1: Fuente exacta (archivo, sección, página o diapositiva)
A2: 1 | B2: 1. Fundamentos y preparación de datos | C2: FUNDAMENTOS Y PREPARACIÓN DE DATOS | D2: 0 | E2: 🟢 Comprendido | F2: Es la base del curso: aprender a organizar un proyecto, distinguir tipos de aprendizaje, leer una tabla de datos y prepararla. Si entiendes estas piezas, puedes interpretar por qué un modelo funciona o falla. | G2: Repasar CRISP-DM y tipos de aprendizaje primero; luego las 4 técnicas de limpieza en orden (normalización, outliers, imputación, selección). | H2: Alta | I2: 27/09/2026 | J2: 02_tema1_fundamentos_y_preparacion_datos.txt | K2: Bloque 1: método de trabajo (CRISP-DM), tipos de aprendizaje, estructura de una tabla de datos (instancias, atributos, clase) y cuatro técnicas de preparación: normalizar o estandarizar, detectar outliers, imputar ausentes y seleccionar atributos. | L2: Ruta mínima de un proyecto: definir la pregunta, mirar los datos, limpiarlos, separar entrenamiento y test, entrenar, evaluar. | M2: Toda transformación que aprende algo de los datos (mínimo, media, mediana de relleno, atributos elegidos) se aprende solo con entrenamiento. | N2: ¿Por qué la preparación de datos es la fase donde un error pasa más desapercibido? | O2: Archivo 02 (manual PDF p.6-31 + 3 notebooks).
A3: 1.1 | B3: 1. Fundamentos y preparación de datos | C3: Metodología CRISP-DM | D3: 1 | E3: 🟢 Comprendido | F3: Es el método más usado para llevar un proyecto de aprendizaje automático de principio a fin. Tiene 6 fases que se siguen en orden, pero se puede volver atrás y repetir pasos. Sirve para no improvisar y mantener el trabajo ordenado. | G3: Aplicar las 6 fases a un caso real y ubicar en qué fase encaja cada tarea del curso (limpieza, modelado, evaluación). | H3: Alta | I3: 27/09/2026 | J3: 02_tema1_fundamentos_y_preparacion_datos.txt | K3: CRISP-DM (Cross-Industry Standard Process for Data Mining): concebido a fines de 1996, proyecto europeo de 1997 codirigido por SPSS, Teradata, NCR, Daimler AG y Ohra; primera versión en 1999. Seis fases con dependencias secuenciales y cíclicas. Alternativas: KDD (1996, sin comprensión del negocio ni despliegue), SEMMA y ASUM-DM (IBM, 2015). | L3: Fases: 1 comprensión del negocio, 2 comprensión de los datos, 3 preparación, 4 modelado, 5 evaluación de negocio, 6 despliegue; se puede volver atrás desde cualquiera. | M3: No es una secuencia rígida: un hallazgo en la evaluación puede obligar a redefinir el objetivo o a preparar de nuevo los datos. | N3: ¿Por qué la evaluación de negocio (fase 5) no es lo mismo que medir la exactitud del modelo? | O3: 02 §1; PDF p.7-8.
A4: 1.1.a | B4: 1. Fundamentos y preparación de datos | C4: Fase 1: Comprensión del negocio | D4: 2 | E4: 🟢 Comprendido | F4: Es el primer paso, y se retoma durante todo el proyecto: definir qué quiere lograr el negocio y cómo sabrán que salió bien, revisar la situación actual, traducir esas metas a tareas técnicas y armar un plan. Así se evita trabajar sin rumbo. | H4: Media | I4: 27/09/2026 | J4: 02_tema1_fundamentos_y_preparacion_datos.txt | K4: Tareas: determinar objetivos de negocio y criterios de éxito (cualitativos o cuantitativos), evaluar la situación actual, determinar los objetivos de minería de datos (traducir metas de negocio a metas técnicas) y producir un plan de proyecto. Debe retomarse durante todo el proyecto. | L4: Negocio: reducir la fuga de clientes. Meta técnica: predecir la baja del próximo mes con la información disponible al inicio de ese mes. | M4: Sin criterio de éxito fijado antes, cualquier resultado se puede presentar como bueno. | N4: ¿Qué diferencia hay entre un objetivo de negocio y un objetivo de minería de datos? | O4: 02 §1; PDF p.10-15 (detalle de las fases).
A5: 1.1.b | B5: 1. Fundamentos y preparación de datos | C5: Fase 2: Comprensión de los datos | D5: 2 | E5: 🟢 Comprendido | F5: Se reúnen los datos y se los revisa por primera vez: se describen, se resumen con números y gráficos de barras, y se busca si faltan datos o hay valores imposibles. Hacerlo bien ahorra tiempo en el resto del proyecto. | H5: Media | I5: 27/09/2026 | J5: 02_tema1_fundamentos_y_preparacion_datos.txt | K5: Tareas: recolectar datos iniciales, describirlos (filas, columnas, significado, formato), explorarlos (estadística descriptiva, tablas de frecuencia, histogramas) y verificar su calidad (nulos, valores fuera de rango, consistencia). Reduce el tiempo total y aumenta las garantías de éxito. | L5: Revisar con describe() y isna().sum() cuántos nulos y qué rangos tiene cada columna antes de modelar. | M5: Saltarse esta fase suele costar más tiempo después, cuando el modelo falla por datos mal entendidos. | N5: ¿Qué dos hallazgos de esta fase cambiarían tu plan de preparación? | O5: 02 §1; PDF p.10-15 (detalle de las fases).
A6: 1.1.c | B6: 1. Fundamentos y preparación de datos | C6: Fase 3: Preparación de los datos | D6: 2 | E6: 🟢 Comprendido | F6: Es la fase más crítica: se eligen, limpian y arreglan los datos para que el modelo (el programa que aprende) pueda usarlos. Si un error pasa sin detectarse aquí, llega al modelo y arruina sus resultados. | H6: Alta | I6: 27/09/2026 | J6: 02_tema1_fundamentos_y_preparacion_datos.txt | K6: Seleccionar, limpiar y generar los conjuntos preparados para modelar. Tareas: seleccionar datos; limpiar (selección de columnas, reducción de filas, normalización, discretización, outliers, imputación); construir datos (p. ej. superficie = largo x ancho); integrar (fusionar tablas); formatear sin cambiar el contenido. Es la fase más crítica y la que más tiempo consume. | L6: Crear la columna superficie = largo x ancho y rellenar las edades ausentes con la mediana de entrenamiento. | M6: Los errores no detectados aquí se trasladan al modelado y son difíciles de rastrear. | N6: ¿Por qué un error de preparación es más peligroso que un error del algoritmo? | O6: 02 §1; PDF p.10-15 (detalle de las fases).
A7: 1.1.d | B7: 1. Fundamentos y preparación de datos | C7: Fase 4: Modelado | D7: 2 | E7: 🟢 Comprendido | F7: Es la fase central de la asignatura: se eligen los algoritmos (métodos de cálculo), se define cómo probarlos y con qué medidas, se construyen los modelos y se revisa técnicamente qué tan bien funcionan. | H7: Alta | I7: 27/09/2026 | J7: 02_tema1_fundamentos_y_preparacion_datos.txt | K7: Crear modelos de conocimiento (clasificación, regresión, etc.) con los datos preparados. Subtareas: seleccionar algoritmos (criterios: tipo de aprendizaje, compatibilidad con los datos, complejidad, interpretabilidad: caja blanca frente a caja negra), generar el plan de prueba (parámetros, métricas, forma de validar), construir los modelos y evaluar técnicamente (ranking de algoritmos). | L7: Comparar regresión logística y un árbol con la misma validación cruzada y las mismas métricas. | M7: Un modelo más complejo no siempre es mejor: se compara con la misma validación y se considera la interpretabilidad. | N7: ¿Qué ventaja tiene un modelo de caja blanca frente a uno de caja negra? | O7: 02 §1; PDF p.10-15 (detalle de las fases).
A8: 1.1.e | B8: 1. Fundamentos y preparación de datos | C8: Fase 5: Evaluación de negocio | D8: 2 | E8: 🟢 Comprendido | F8: Se comprueba si los modelos cumplen lo que el negocio pidió al inicio como éxito. También se revisa cómo se trabajó y se decide si terminar, repetir pasos o iniciar nuevos proyectos. Así se confirma que el resultado sirve de verdad. | H8: Media | I8: 27/09/2026 | J8: 02_tema1_fundamentos_y_preparacion_datos.txt | K8: Evaluar los modelos frente a los criterios de éxito de negocio definidos al inicio. Tareas: evaluar resultados, revisar el proceso (aseguramiento de calidad) y determinar los siguientes pasos (finalizar, iterar o abrir nuevos subproyectos). | L8: Un modelo con buena exactitud puede no cumplir el criterio de negocio si no detecta los casos costosos. | M8: Es una evaluación contra el objetivo del negocio, no solo contra una métrica técnica. | N8: ¿Qué tres decisiones puede tomar el equipo al cerrar esta fase? | O8: 02 §1; PDF p.10-15 (detalle de las fases).
A9: 1.1.f | B9: 1. Fundamentos y preparación de datos | C9: Fase 6: Despliegue | D9: 2 | E9: 🟢 Comprendido | F9: Lo aprendido se convierte en acciones reales dentro del negocio: se planea cómo ponerlo en uso, se vigila y mantiene, se escribe un informe final y se revisa el proyecto. Sin este paso, el análisis queda sin utilidad práctica. | H9: Media | I9: 27/09/2026 | J9: 02_tema1_fundamentos_y_preparacion_datos.txt | K9: Transformar el conocimiento obtenido en acciones dentro del proceso de negocio. Tareas: planear la implementación, monitorizar y mantener (detectar comportamientos anómalos), crear el informe final y revisar el proyecto (lecciones aprendidas). | L9: Poner el modelo a puntuar cada noche y vigilar si su rendimiento cae con el tiempo. | M9: Un modelo desplegado se degrada si cambian los datos: requiere monitorización. | N9: ¿Por qué hay que seguir vigilando un modelo después de desplegarlo? | O9: 02 §1; PDF p.10-15 (detalle de las fases).
A10: 1.1.g | B10: 1. Fundamentos y preparación de datos | C10: Roles en ciencia de datos | D10: 2 | E10: 🟢 Comprendido | F10: Un equipo que trabaja con datos suele tener cuatro roles: director técnico (data scientist chief), científico de datos (data scientist), analista de datos (data analyst) e ingeniero de datos (data engineer). Cada uno cumple una función distinta dentro del proyecto. | H10: Baja | I10: 27/09/2026 | J10: 02_tema1_fundamentos_y_preparacion_datos.txt | K10: Cuatro roles típicos: director técnico (data scientist chief: planifica, asigna recursos, valida), científico de datos (data scientist: analiza, diseña, experimenta, interpreta), analista de datos (data analyst: inteligencia de negocio, informes, cuadros de mando) e ingeniero de datos (data engineer: extrae, limpia, transforma, carga y automatiza). También hay ingenieros de software, administradores de BD y diseñadores gráficos. | L10: El ingeniero de datos arma el flujo que carga las tablas; el científico de datos construye el modelo sobre ellas. | M10: Es un complemento del manual (apartado 1.1.3): no forma parte de CRISP-DM en sí. | N10: ¿Qué rol se encarga de automatizar la carga y transformación de los datos? | O10: 02 §1; PDF p.9.
A11: 1.2 | B11: 1. Fundamentos y preparación de datos | C11: Tipos de aprendizaje (supervisado / no supervisado / otros) | D11: 1 | E11: 🟢 Comprendido | F11: Hay dos grandes tipos de aprendizaje. Si los datos incluyen la respuesta que se quiere acertar, es supervisado: se usa para predecir. Si no la incluyen, es no supervisado. También existen variantes intermedias, como semisupervisado y por refuerzo. | G11: Practicar clasificando problemas reales como regresión, clasificación, clustering o reglas de asociación. | H11: Alta | I11: 27/09/2026 | J11: 02_tema1_fundamentos_y_preparacion_datos.txt | K11: Dos categorías: problemas con variable de salida (supervisado) y sin ella (no supervisado). Otros tipos: semisupervisado y por refuerzo. Además existen tareas de apoyo como la reducción de dimensionalidad, la discretización o la selección de instancias y atributos. | L11: Predecir el precio de una casa con ejemplos de precios conocidos es supervisado; agrupar clientes parecidos sin etiqueta es no supervisado. | M11: Que una columna esté escrita con números no la convierte en regresión: los códigos 0 y 1 pueden ser clases. | N11: ¿Qué dato necesitas para que un problema sea supervisado? | O11: 02 §2; PDF p.15-17.
A12: 1.2.a | B12: 1. Fundamentos y preparación de datos | C12: Aprendizaje supervisado: regresión vs. clasificación | D12: 2 | E12: 🟢 Comprendido | F12: Aquí se calcula una respuesta a partir de los demás datos. Si la respuesta es un número, se llama regresión; si es una categoría o etiqueta, clasificación. Todas las filas necesitan tener su respuesta, porque de ahí aprende el modelo. | H12: Alta | I12: 27/09/2026 | J12: 02_tema1_fundamentos_y_preparacion_datos.txt | K12: Se estima el valor de la variable de salida a partir del resto de variables. Regresión: salida numérica (número real). Clasificación: salida categórica (etiqueta o número discreto). Es imprescindible que todas las filas tengan valor de salida; sin él, esa fila no aporta aprendizaje. | L12: Precio de la vivienda: regresión. Especie de iris (setosa, versicolor, virginica): clasificación. | M12: Una columna numérica puede ser una clase (0 y 1); y una entrada categórica puede usarse en regresión tras codificarla. | N12: Si la salida es la talla S, M o L, ¿es regresión o clasificación y por qué? | O12: 02 §2; PDF p.15-16.
A13: 1.2.b | B13: 1. Fundamentos y preparación de datos | C13: Aprendizaje no supervisado: clustering y reglas de asociación | D13: 2 | E13: 🟢 Comprendido | F13: Sin respuesta que acertar, no se predice. El clustering (agrupamiento) junta datos parecidos. Las reglas de asociación dicen que si pasa algo (antecedente), suele pasar otra cosa (consecuente). Sirven, por ejemplo, para recomendar productos. | H13: Media | I13: 27/09/2026 | J13: 02_tema1_fundamentos_y_preparacion_datos.txt | K13: Sin variable de salida no hay inferencia ni predicción. Clustering: crear grupos de datos similares. Reglas de asociación: reglas antecedente-consecuente que asocian variables, útiles para dependencias y recomendación. | L13: Cesta de la compra: si compra pan y leche (antecedente), suele comprar mantequilla (consecuente). | M13: Un grupo hallado por clustering no trae nombre: el significado lo pone la persona. | N13: ¿Por qué agrupar clientes por parecido no basta para saber qué grupo es el de los que se irán? | O13: 02 §2; PDF p.16.
A14: 1.2.c | B14: 1. Fundamentos y preparación de datos | C14: Reducción de dimensionalidad | D14: 2 | E14: 🟢 Comprendido | F14: Consiste en achicar la cantidad de datos, quitando filas o columnas o transformando los valores, para que el trabajo sea más rápido sin perder calidad. Puede hacerse con o sin una respuesta conocida en los datos. | H14: Media | I14: 27/09/2026 | J14: 02_tema1_fundamentos_y_preparacion_datos.txt | K14: Reduce el volumen de datos antes de modelar, eliminando filas o columnas o transformando el espacio de valores, para mantener o mejorar la eficacia y aumentar la eficiencia. Puede ser supervisada o no supervisada. | L14: Seleccionar las 10 columnas más relacionadas con la clase antes de entrenar un KNN. | M14: Reducir sin criterio puede perder justo la información útil. | N14: ¿Qué dos formas hay de reducir la dimensionalidad? | O14: 02 §2; PDF p.16.
A15: 1.2.d | B15: 1. Fundamentos y preparación de datos | C15: Aprendizaje semisupervisado | D15: 2 | E15: 🟢 Comprendido | F15: Los datos tienen una respuesta a acertar, pero solo en algunas filas. En lugar de borrar las filas que no la tienen, se usan modelos que aprovechan todos los datos disponibles, así no se desperdicia información. | H15: Baja | I15: 27/09/2026 | J15: 02_tema1_fundamentos_y_preparacion_datos.txt | K15: Hay variable de salida, pero no todas las filas tienen valor. En vez de eliminar las filas sin valor, se construyen modelos que aprovechan todas. | L15: 1000 fotos, de las cuales solo 100 tienen su etiqueta confirmada. | M15: Se diferencia del supervisado puro, que exige salida en todas las filas. | N15: ¿Qué problema evita el semisupervisado que el supervisado puro no resuelve? | O15: 02 §2; PDF p.16-17.
A16: 1.2.e | B16: 1. Fundamentos y preparación de datos | C16: Aprendizaje por refuerzo | D16: 2 | E16: 🟢 Comprendido | F16: El algoritmo no recibe la respuesta correcta exacta, sino una valoración de si lo que respondió estuvo bien o mal. Si acierta, se parece al supervisado; si falla, solo sabe que su respuesta no fue adecuada. | H16: Baja | I16: 27/09/2026 | J16: 02_tema1_fundamentos_y_preparacion_datos.txt | K16: El aprendiz recibe una valoración sobre la idoneidad de su respuesta. Con respuestas correctas se parece al supervisado; con errores solo se informa que fue inadecuada, a veces con una estimación del error, no el valor exacto de la respuesta correcta. | L16: Un agente que aprende a jugar recibe puntos o castigos, no la jugada correcta. | M16: En supervisado se puede calcular el error exacto; en refuerzo no necesariamente. | N16: ¿Qué recibe el aprendiz en refuerzo cuando se equivoca, a diferencia del supervisado? | O16: 02 §2; PDF p.17.
A17: 1.2.f | B17: 1. Fundamentos y preparación de datos | C17: Frontera de decisión / frontera bayesiana | D17: 2 | E17: 🟡 Repasar | F17: La frontera de decisión es la línea que separa un grupo de otro. En el caso ideal, si se conocen las reglas exactas de los datos, se calcula la mejor frontera. En la práctica solo hay una muestra, y la frontera estimada mejora cuantos más datos haya. | H17: Media | I17: 27/09/2026 | J17: 02_tema1_fundamentos_y_preparacion_datos.txt | K17: Frontera de decisión: lugar donde el clasificador cambia de una clase a otra. Caso ideal: si se conocen las distribuciones de origen, la frontera óptima (bayesiana) se calcula analíticamente. Caso real: solo hay una muestra y la frontera se estima; mejora con más datos (el notebook compara 10, 100 y 10000 puntos). | L17: Notebook: LogisticRegression (frontera lineal), RandomForestClassifier y SVC sobre los mismos datos 2D. | M17: Todo algoritmo asume algo (normalidad, independencia, forma lineal o cuadrática de la frontera). | N17: ¿Por qué la frontera estimada con 10 puntos suele ser peor que con 10000? | O17: 02 §2 (complemento del notebook de terminología).
A18: 1.3 | B18: 1. Fundamentos y preparación de datos | C18: Estructura de datos: instancias, atributos y clase | D18: 1 | E18: 🟢 Comprendido | F18: Los datos se organizan en una tabla: cada fila es una instancia (un caso) y cada columna es un atributo (un dato descriptivo). Además está la clase, que es la respuesta a predecir. Se anotan como X (atributos) e y (clase). | G18: Practicar identificando instancias, atributos y clase en un dataset real como iris o penguins. | H18: Alta | I18: 27/09/2026 | J18: 02_tema1_fundamentos_y_preparacion_datos.txt | K18: La estructura fundamental es la tabla de datos (dataset): dos dimensiones, columnas de un solo tipo cada una. Cada celda es numérica (float) o categórica (cadena, booleano, entero). Nomenclatura: instancia = fila; atributo = columna de entrada; clase = salida; modelo = lo que extrae el algoritmo. | L18: Iris: 150 instancias, 4 atributos numéricos (sepal-length, sepal-width, petal-length, petal-width), clase con 3 valores, 0 ausentes. | M18: Existen otras estructuras (grafos, series temporales, secuencias, jerarquías) que el curso no desarrolla aquí. | N18: En una tabla de pacientes, ¿qué columna sería la clase y cuáles los atributos? | O18: 02 §3; PDF p.17-19.
A19: 1.3.a | B19: 1. Fundamentos y preparación de datos | C19: Instancia | D19: 2 | E19: 🟢 Comprendido | F19: Es cada fila de la tabla de datos, o sea un caso individual. También se le llama ejemplo, muestra, observación o punto. Por ejemplo, una persona o una flor dentro de la tabla. | H19: Alta | I19: 27/09/2026 | J19: 02_tema1_fundamentos_y_preparacion_datos.txt | K19: Instancia = cada fila de la tabla (también ejemplo, muestra, observación, punto o prototipo; en inglés instance, data point, sample). | L19: Una flor concreta del dataset iris. | M19: No es lo mismo que una característica: la instancia es la fila entera. | N19: Si la tabla tiene 150 filas, ¿cuántas instancias hay? | O19: 02 §3; PDF p.18.
A20: 1.3.b | B20: 1. Fundamentos y preparación de datos | C20: Atributo / característica | D20: 2 | E20: 🟢 Comprendido | F20: Es cada columna de la tabla, excepto la que tiene la respuesta. Describe una característica de cada caso. También se le llama característica, feature, variable de entrada o predictora. | H20: Alta | I20: 27/09/2026 | J20: 02_tema1_fundamentos_y_preparacion_datos.txt | K20: Atributo = cada columna excepto la clase (también característica, causa, variable de entrada, variable explicativa; attribute, feature, predictor). El notebook los usa indistintamente: 'atributo' y 'característica'. | L20: sepal-length y petal-width en iris. | M20: Un atributo medido después del resultado (por ejemplo la nota final) no sirve para predecir con antelación. | N20: ¿Por qué un atributo registrado después del resultado puede ser inútil en la práctica? | O20: 02 §3; PDF p.18.
A21: 1.3.c | B21: 1. Fundamentos y preparación de datos | C21: Clase / variable objetivo | D21: 2 | E21: 🟢 Comprendido | F21: Es la respuesta que se quiere predecir en el aprendizaje supervisado. También se llama etiqueta, target o respuesta. Es un número en regresión y una categoría en clasificación. | H21: Alta | I21: 27/09/2026 | J21: 02_tema1_fundamentos_y_preparacion_datos.txt | K21: Clase = variable de salida del aprendizaje supervisado (también etiqueta, variable objetivo, respuesta, efecto, consecuencia; class, target, response). Numérica en regresión (y_i real) y categórica en clasificación (dominio {c1,...,cm}). | L21: La columna especie de iris, con dominio {setosa, versicolor, virginica}. | M21: Una clase con códigos numéricos sigue siendo categórica. | N21: ¿Cuál es la clase si quieres predecir si un cliente comprará? | O21: 02 §3; PDF p.18.
A22: 1.3.d | B22: 1. Fundamentos y preparación de datos | C22: Notación formal X, y, eᵢ, xⱼ, xᵢⱼ | D22: 2 | E22: 🟡 Repasar | F22: Es la forma de escribir la tabla con símbolos: X guarda todos los atributos de las n instancias (p atributos por instancia); y es la lista de respuestas; eᵢ es la fila i; xⱼ es la columna j; xᵢⱼ es el valor de la columna j en la fila i. | H22: Alta | I22: 27/09/2026 | J22: 02_tema1_fundamentos_y_preparacion_datos.txt | K22: La tabla tiene n instancias y p atributos. X = matriz de atributos; y = vector de clase; e_i = instancia (fila) i; x_j = atributo (columna) j; x_ij = valor del atributo j en la instancia i (i = 1..n, j = 1..p). En programación: X (matriz o DataFrame) e y (vector). | L22: Con 150 filas y 4 columnas, X tiene forma (150, 4) e y tiene forma (150,). | M22: No confundir x_ij (un valor) con x_j (toda la columna) ni con e_i (toda la fila). | N22: ¿Qué representa x_(3,2) en una tabla de pacientes? | O22: 02 §3; PDF p.18-19 (Tabla 1).
A23: 1.3.e | B23: 1. Fundamentos y preparación de datos | C23: Parámetros vs. hiperparámetros | D23: 2 | E23: 🟢 Comprendido | F23: Los parámetros son valores del modelo que se ajustan solos mientras aprende. Los hiperparámetros son ajustes del método de aprendizaje que la persona fija antes de empezar y que no cambian durante el entrenamiento. | H23: Media | I23: 27/09/2026 | J23: 02_tema1_fundamentos_y_preparacion_datos.txt | K23: Parámetros: pertenecen al modelo y se ajustan durante el entrenamiento. Hiperparámetros: pertenecen al algoritmo de aprendizaje, se fijan antes de entrenar y permanecen constantes durante él. Otros términos del notebook: datos de entrenamiento, datos de prueba (test) y métrica. | L23: Parámetro: el coeficiente w1 de una regresión. Hiperparámetro: el número de vecinos k de un KNN. | M23: Los hiperparámetros se eligen con validación, nunca mirando el test. | N23: ¿El número de vecinos k es un parámetro o un hiperparámetro? | O23: 02 §3 (complemento del notebook de terminología).
A24: 1.3.f | B24: 1. Fundamentos y preparación de datos | C24: Características de un conjunto de datos | D24: 2 | E24: 🟡 Repasar | F24: Al empezar un proyecto se anota un resumen de los datos: cuántas filas y columnas hay, de qué tipo es cada columna y la respuesta, y cuántos valores faltan. Ejemplo, iris: 150 instancias, 4 atributos, 3 clases, 0 faltantes. | H24: Baja | I24: 27/09/2026 | J24: 02_tema1_fundamentos_y_preparacion_datos.txt | K24: Al inicio de un proyecto se anota: número de instancias, número de atributos, nombre, tipo y breve descripción de cada atributo, tipo y dominio de la clase, descripción de la clase y cantidad de valores ausentes. | L24: Iris: 150 instancias, 4 atributos numéricos, clase categórica de 3 valores, 0 ausentes. | M24: Una ficha incompleta oculta problemas (ausentes, tipos mal leídos) que aparecen tarde. | N24: ¿Qué cinco datos anotarías de una tabla nueva antes de modelar? | O24: 02 §3; PDF p.19.
A25: 1.4 | B25: 1. Fundamentos y preparación de datos | C25: Limpieza de datos — introducción | D25: 1 | E25: 🟢 Comprendido | F25: Es una tarea clave dentro de la preparación de datos: quita defectos y ajusta los datos para que sus patrones se vean con la mayor claridad posible. Se hace antes de entrenar el modelo para que aprenda de datos limpios. | G25: Repasar junto con las 4 técnicas concretas (normalización, outliers, imputación, selección) que desarrollan esta fase. | H25: Media | I25: 27/09/2026 | J25: 02_tema1_fundamentos_y_preparacion_datos.txt | K25: Eliminación de defectos de los datos y adaptación para el modelado, dentro de la fase de preparación de CRISP-DM. Busca la forma de los datos que exponga sus patrones con más nitidez. El manual estudia: normalización y estandarización, outliers, imputación y selección de atributos; menciona sin desarrollar la discretización, la generación de atributos y la selección de instancias. | L25: Pipeline típico: imputar, escalar y seleccionar atributos, siempre ajustado con entrenamiento. | M25: La limpieza puede ser supervisada o no supervisada según use o no la clase. | N25: ¿Por qué se considera la limpieza parte de la preparación y no del modelado? | O25: 02 §4; PDF p.19-20.
A26: 1.4.a | B26: 1. Fundamentos y preparación de datos | C26: Técnicas de fila, columna o matriz completa | D26: 2 | E26: 🟡 Repasar | F26: Las técnicas de limpieza se clasifican según la parte de la tabla que modifican: una fila, una columna (como la normalización, que cambia una columna entera) o la tabla completa. | H26: Baja | I26: 27/09/2026 | J26: 02_tema1_fundamentos_y_preparacion_datos.txt | K26: Según la parte de la tabla sobre la que actúan: técnicas de fila, de columna o de matriz completa. La normalización es una técnica de columna porque actúa sobre todos los valores de una columna a la vez. | L26: Imputar actúa por columna; eliminar duplicados actúa sobre filas. | M26: Es una clasificación de apoyo; no cambia cómo se calcula cada técnica. | N26: ¿La normalización es una técnica de fila, de columna o de matriz completa? | O26: 02 §4; PDF p.20.
A27: 1.4.b | B27: 1. Fundamentos y preparación de datos | C27: Limpieza supervisada vs. no supervisada | D27: 2 | E27: 🟢 Comprendido | F27: Igual que en el aprendizaje automático, algunas técnicas de limpieza necesitan que los datos incluyan la respuesta a predecir (la clase) y otras funcionan sin ella. | H27: Baja | I27: 27/09/2026 | J27: 02_tema1_fundamentos_y_preparacion_datos.txt | K27: Como en el aprendizaje automático, las técnicas de limpieza pueden ser supervisadas (usan la clase) o no supervisadas (no la usan). | L27: Baja varianza: no supervisada. F-test: supervisada. | M27: Una técnica supervisada que usa la clase de todo el conjunto antes de separar test provoca fuga de información. | N27: ¿Por qué una selección supervisada debe ajustarse solo con entrenamiento? | O27: 02 §4; PDF p.20.
A28: 1.5 | B28: 1. Fundamentos y preparación de datos | C28: Normalización y estandarización | D28: 1 | E28: 🟢 Comprendido | F28: Son dos técnicas para poner los datos numéricos en una escala parecida. Se hace para que una columna con números muy grandes no pese más que otra igual de importante. Normalización: (x − mínimo)/(máximo − mínimo). Estandarización: (x − media)/desviación. | G28: Practicar aplicando MinMaxScaler y StandardScaler con fit en train y transform en test. | H28: Alta | I28: 27/09/2026 | J28: 02_tema1_fundamentos_y_preparacion_datos.txt | K28: Normalización: lleva cada atributo numérico a [0,1] con x_N = (x - min) / (max - min) (centrado y escalado por el rango). Estandarización: x_S = (x - media) / desviación típica (centrado en la media y escalado por la desviación). Se aplican columna por columna. | L28: X_train = [[1,-1,2],[2,0,0],[0,1,-1]]; MinMaxScaler().fit_transform(X_train) da [[0.5,0,1],[1,0.5,0.333],[0,1,0]]. | M28: Ajusta (fit) con entrenamiento y aplica (transform) a test sin reajustar. | N28: ¿Qué problema evitan ambas técnicas cuando se usan distancias entre casos? | O28: 02 §5; PDF p.20-22.
A29: 1.5.a | B29: 1. Fundamentos y preparación de datos | C29: Normalización | D29: 2 | E29: 🟢 Comprendido | F29: Lleva los valores de una columna al rango de 0 a 1: se resta el menor valor y se divide por la diferencia entre el mayor y el menor. Se aplica columna por columna. Así todas quedan en la misma escala. | H29: Alta | I29: 27/09/2026 | J29: 02_tema1_fundamentos_y_preparacion_datos.txt | K29: x_N = (x - min(x_i)) / (max(x_i) - min(x_i)). Restar el mínimo = centrado; dividir por el rango = escalado. Para desnormalizar: x = x_N (max - min) + min. Es una homotecia aplicada a cada columna. | L29: Un atributo con mínimo 0 y máximo 2: 0 pasa a 0, 1 pasa a 0,5 y 2 pasa a 1. Clase: preprocessing.MinMaxScaler. | M29: Con datos futuros fuera del rango de entrenamiento el resultado puede salir de [0,1]; y si max = min la fórmula no está definida. | N29: Si el máximo de entrenamiento es 60 y llega un caso con 70, ¿cuánto vale su normalizado con mínimo 20? | O29: 02 §5; PDF p.20-21 (Programa 1).
A30: 1.5.b | B30: 1. Fundamentos y preparación de datos | C30: Estandarización | D30: 2 | E30: 🟢 Comprendido | F30: Ajusta una columna para que quede centrada en su promedio (media) y medida según cuánto se alejan los valores de él (desviación típica). A diferencia de la normalización, los valores no quedan limitados a un rango fijo. | H30: Alta | I30: 27/09/2026 | J30: 02_tema1_fundamentos_y_preparacion_datos.txt | K30: x_S = (x - media(x_i)) / desviación(x_i). El escalado cubre solo la amplitud de la desviación típica, por lo que los valores no quedan acotados a un rango fijo. Desestandarizar: x = x_S desv + media. | L30: Primer atributo del ejemplo del PDF: media 1, desviación 0,8165; el valor 2 pasa a (2-1)/0,8165 = 1,22474. Clase: preprocessing.StandardScaler. | M30: Si la desviación es cero la fórmula exige un tratamiento especial. | N30: Si un valor estandarizado es 0, ¿qué significa respecto a la media? | O30: 02 §5; PDF p.22 (Programa 2).
A31: 1.5.c | B31: 1. Fundamentos y preparación de datos | C31: Cuándo usar cada técnica | D31: 2 | E31: 🟢 Comprendido | F31: Se usa normalización cuando el algoritmo no supone nada sobre cómo se reparten los valores. Se usa estandarización cuando el algoritmo sí supone que los datos siguen la forma de campana (distribución normal). | H31: Media | I31: 27/09/2026 | J31: 02_tema1_fundamentos_y_preparacion_datos.txt | K31: Criterio práctico del notebook: normalización para algoritmos que no presuponen una distribución de los datos; estandarización cuando el algoritmo sí presupone normalidad. Ambas son muy recomendables si se usan distancias o productos escalares. | L31: KNN (basado en distancias) suele necesitar estandarizar; un árbol de decisión es independiente de la escala. | M31: Cambiar la escala no vuelve relevante un atributo que no lo era. | N31: ¿Qué técnica elegirías si el algoritmo supone datos con distribución normal? | O31: 02 §5 (notebook limpieza_datos_1).
A32: 1.5.d | B32: 1. Fundamentos y preparación de datos | C32: Evitar fuga de información (data leakage) | D32: 2 | E32: 🟢 Comprendido | F32: Al separar los datos en entrenamiento (train) y prueba (test), la transformación se calcula solo con los de entrenamiento y luego se aplica igual a los de prueba, sin recalcularla. Así la prueba no "espía" información que el modelo no debería conocer. | H32: Alta | I32: 27/09/2026 | J32: 02_tema1_fundamentos_y_preparacion_datos.txt | K32: Al dividir en train y test, el normalizador o estandarizador se ajusta (fit) solo con train y se aplica (transform) tal cual a test; nunca se reajusta con test. Así el test no influye en la preparación del modelo (fuga de información o data leakage). | L32: f = normalizer.fit(X_train); X_train_n = f.transform(X_train); X_test_n = f.transform(X_test) (sin fit). | M32: Calcular el mínimo y el máximo con toda la tabla antes de separar contamina el test. | N32: ¿Por qué calcular la media con todos los datos antes de separar el test deja de ser una prueba independiente? | O32: 02 §5 (notebook); 03 §0.
A33: 1.6 | B33: 1. Fundamentos y preparación de datos | C33: Detección de outliers | D33: 1 | E33: 🟢 Comprendido | F33: Un outlier es un dato muy raro frente al resto, y puede confundir a los modelos y bajar su calidad. Esta etapa busca esos casos. No hay una línea exacta que separe lo raro de lo normal, así que el límite suele ser difuso. | G33: Practicar EllipticEnvelope y el método boxplot sobre el dataset outliers.csv. | H33: Alta | I33: 27/09/2026 | J33: 02_tema1_fundamentos_y_preparacion_datos.txt | K33: Un outlier es un valor fuera de la distribución natural de los datos que puede reducir la eficacia de los modelos. El umbral entre outlier y no-outlier no es trivial: la frontera suele ser difusa. El manual desarrolla un algoritmo (envolvente elíptica); el notebook añade el método de cajas y bigotes y otros detectores. | L33: outliers.csv: 200 instancias, 2 atributos, 150 normales y 50 outliers, rango [-7, 7]. | M33: Un valor extremo puede ser un error o un caso real: investígalo antes de borrarlo. | N33: ¿Por qué encontrar un valor sorprendente no demuestra por sí solo que deba eliminarse? | O33: 02 §6; PDF p.23-26.
A34: 1.6.a | B34: 1. Fundamentos y preparación de datos | C34: Envolvente elíptica (EllipticEnvelope) | D34: 2 | E34: 🟢 Comprendido | F34: Supone que los datos se reparten como una campana: muchos en el centro y pocos lejos. Dibuja una elipse (óvalo) alrededor de los puntos normales. Mientras más grande es la elipse que hace falta para incluir un punto, más lejos está y más probable es que sea un outlier. Se usa con sklearn.covariance.EllipticEnvelope. | H34: Alta | I34: 27/09/2026 | J34: 02_tema1_fundamentos_y_preparacion_datos.txt | K34: EllipticEnvelope: supone distribución normal; crea superficies elípticas alrededor de los puntos normales; cuanto mayor la elipse que engloba un punto, mayor su distancia y su probabilidad de ser outlier. Los datos se centran y escalan con mediana e IQR. | L34: EllipticEnvelope().fit(df); decision_function(df) puntúa la normalidad de cada instancia. | M34: Si los datos no son normales puede haber falsos positivos y falsos negativos. | N34: ¿Qué supuesto sobre la distribución hace la envolvente elíptica? | O34: 02 §6; PDF p.24-26 (Programa 3).
A35: 1.6.b | B35: 1. Fundamentos y preparación de datos | C35: Mediana e IQR como base del cálculo | D35: 2 | E35: 🟢 Comprendido | F35: El centro de las elipses se calcula con la mediana (el valor del medio) y el IQR (el ancho de la zona donde está la mitad central de los datos), no con el promedio. El motivo: los propios outliers deforman el promedio. IQR = P75 - P25; umbral típico: mediana ± 1,5·IQR o ± 3·IQR. | H35: Media | I35: 27/09/2026 | J35: 02_tema1_fundamentos_y_preparacion_datos.txt | K35: Se usa la mediana en vez de la media porque la media se distorsiona con los propios outliers. IQR = P75 - P25. Todo valor que supere la mediana más o menos un umbral (típicamente 1,5 IQR, moderado, o 3 IQR, extremo) se considera outlier. | L35: Q1 = scoreatpercentile(a, 25); Q3 = scoreatpercentile(a, 75); IQR = Q3 - Q1. | M35: 1,5 IQR y 3 IQR son convenciones, no verdades: cambian cuántos puntos se marcan. | N35: ¿Por qué la mediana resiste mejor a los outliers que la media? | O35: 02 §6; PDF p.24.
A36: 1.6.c | B36: 1. Fundamentos y preparación de datos | C36: Umbral por percentil vs. contamination fijo | D36: 2 | E36: 🟢 Comprendido | F36: Hay dos formas de decidir qué es raro con la misma herramienta. El PDF puntúa cada dato y corta en un percentil (25). El notebook fija de antemano que 25% de los datos serán outliers (contamination=0.25). Cambia solo cómo se pone el corte. | H36: Media | I36: 27/09/2026 | J36: 02_tema1_fundamentos_y_preparacion_datos.txt | K36: Versión PDF: decision_function() puntúa la normalidad y scoreatpercentile(scores_pred, 25) fija el umbral en el percentil 25. Versión notebook: EllipticEnvelope(support_fraction=None, contamination=0.25, random_state=42) y predict() devuelve 1 (normal) o -1 (outlier). Es la misma clase con distinta forma de fijar el corte. | L36: pos_outliers = np.where(predict(df) == -1)[0] da las posiciones de los outliers. | M36: contamination fija de antemano la proporción esperada de outliers: si es incorrecta, el resultado también. | N36: ¿Qué proporción de outliers asume contamination=0.25? | O36: 02 §6 (PDF p.25-26 y notebook limpieza_datos_1).
A37: 1.6.d | B37: 1. Fundamentos y preparación de datos | C37: Método boxplot / cajas y bigotes | D37: 2 | E37: 🔴 Débil | F37: Método solo del notebook, el de cajas y bigotes. Calcula dónde empieza y termina la mitad central de los datos (Q1, Q3, IQR) y marca como outlier todo lo que cae fuera de unos límites. Límite superior = P75+1.5·IQR; límite inferior = P25-1.5·IQR. | H37: Media | I37: 27/09/2026 | J37: 02_tema1_fundamentos_y_preparacion_datos.txt | K37: Método solo del notebook: Q1 = P25, Q3 = P75, RIC = Q3 - Q1. Límite superior = Q3 + 1,5 RIC; límite inferior = Q1 - 1,5 RIC. Se marca outlier lo que cae fuera. Se dibuja con plt.boxplot. | L37: pos_i = np.where(a < li)[0]; pos_s = np.where(a > ls)[0]; pos_outliers = np.concatenate((pos_i, pos_s)). | M37: No está desarrollado en el PDF; solo el concepto de IQR coincide con la envolvente elíptica. | N37: ¿Con qué fórmula se obtiene el límite superior del boxplot? | O37: 02 §6 (solo notebook).
A38: 1.6.e | B38: 1. Fundamentos y preparación de datos | C38: Otros detectores de outliers | D38: 2 | E38: 🔴 Débil | F38: Existen otras herramientas de sklearn para encontrar datos raros: IsolationForest, LocalOutlierFactor y OneClassSVM. Se usan igual que la anterior: primero se ajustan a los datos (fit) y luego marcan cuáles son raros (predict). | H38: Baja | I38: 27/09/2026 | J38: 02_tema1_fundamentos_y_preparacion_datos.txt | K38: Otros detectores de sklearn con el mismo patrón fit y predict: IsolationForest, LocalOutlierFactor, OneClassSVM (se plantean como ejercicio de comparación). | L38: IF = IsolationForest(); df_outliers, pos_outliers = find_outliers(df, IF). | M38: El notebook solo los menciona; no se explica su fundamento. | N38: ¿Qué tienen en común los detectores de outliers de sklearn en cuanto a su uso? | O38: 02 §6 (notebook).
A39: 1.7 | B39: 1. Fundamentos y preparación de datos | C39: Imputación de valores ausentes | D39: 1 | E39: 🔴 Débil | F39: Cuando faltan datos (huecos o NaN), en vez de borrar los registros completos se rellenan con valores estimados. Así se evita perder la información que sí estaba en esos registros. | G39: Practicar SimpleImputer sobre datos reales (penguins.csv) con fit/transform. | H39: Alta | I39: 27/09/2026 | J39: 02_tema1_fundamentos_y_preparacion_datos.txt | K39: Los conjuntos de datos suelen estar incompletos (valores ausentes o missing values; en Python np.nan). Muchos algoritmos de scikit-learn no toleran ausentes. Eliminar las instancias con algún ausente puede perder mucha información; por eso se imputa (se reemplaza por un valor estimado). | L39: SimpleImputer(missing_values=np.nan, strategy='mean'). | M39: Calcula el valor de relleno solo con entrenamiento y aplica el mismo a test. | N39: ¿Por qué borrar todas las filas con ausentes puede ser una mala idea? | O39: 02 §7; PDF p.26-28.
A40: 1.7.a | B40: 1. Fundamentos y preparación de datos | C40: Valores ausentes (missing values) | D40: 2 | E40: 🟢 Comprendido | F40: Son huecos en los datos: la información no se recogió, no estaba disponible, o era errónea y se borró. En Python se marcan con np.nan, que significa 'no es un número'. | H40: Media | I40: 27/09/2026 | J40: 02_tema1_fundamentos_y_preparacion_datos.txt | K40: Valores ausentes: huecos porque la información no pudo recabarse, no estaba disponible o era errónea y se eliminó. Se representan como NaN, NA, N/A o Null; en Python con np.nan. | L40: csv.isna().sum() cuenta los ausentes por columna del dataset penguins. | M40: Un ausente puede significar cosas distintas (no aplica, no se midió, se perdió): averígualo antes de imputar. | N40: ¿Qué función cuenta los valores ausentes por columna en pandas? | O40: 02 §7; PDF p.26.
A41: 1.7.b | B41: 1. Fundamentos y preparación de datos | C41: Por qué no eliminar simplemente las filas | D41: 2 | E41: 🟢 Comprendido | F41: La mayoría de los algoritmos de sklearn no funcionan si hay huecos. Pero borrar todos los registros con huecos puede hacer perder mucha información valiosa. Por eso se prefiere rellenar los huecos. | H41: Media | I41: 27/09/2026 | J41: 02_tema1_fundamentos_y_preparacion_datos.txt | K41: La mayoría de los algoritmos de scikit-learn no admiten ausentes, y eliminar todas las instancias con algún ausente puede suponer una pérdida importante de información; por eso se prefiere reemplazarlos por valores concretos mediante técnicas de imputación. | L41: Cálculo propio: con 5 % de ausentes al azar en 10 columnas independientes, cerca del 40 % de las filas (1 - 0,95 elevado a 10) tendría al menos un ausente y se perdería al borrarlas. | M41: Imputar también introduce suposiciones: no es gratis. | N41: ¿Qué dos riesgos tiene eliminar las filas con ausentes? | O41: 02 §7; PDF p.26-27.
A42: 1.7.c | B42: 1. Fundamentos y preparación de datos | C42: Imputación por media, mediana o moda | D42: 2 | E42: 🟢 Comprendido | F42: Lo más simple es rellenar con un valor típico de esa columna: promedio o mediana si son números, o el valor más repetido (moda) si son categorías. Hay métodos más complejos que usan modelos. Se usa SimpleImputer(strategy='mean'/'median'/'most_frequent'). | H42: Alta | I42: 27/09/2026 | J42: 02_tema1_fundamentos_y_preparacion_datos.txt | K42: Técnica más simple: sustituir por la media o la mediana (atributo numérico) o por la moda (categórico). Hay técnicas más complejas que plantean la imputación como un problema supervisado. En sklearn: SimpleImputer con strategy mean, median o most_frequent. | L42: a = [[1,2],[nan,3],[7,6]]: medias por columna 4 y 3,6667; b = [[nan,10],[6,nan],[8,1]] queda [[4,10],[6,3.6667],[8,1]]. | M42: El ejemplo del PDF llama a transform sin mostrar el fit previo (posible omisión editorial del manual). | N42: ¿Qué estrategia usarías para un atributo categórico? | O42: 02 §7; PDF p.27 (Programa 4).
A43: 1.7.d | B43: 1. Fundamentos y preparación de datos | C43: Fit sobre train, transform sobre train y test | D43: 2 | E43: 🔴 Débil | F43: El rellenador aprende su valor típico (fit) solo con los datos de entrenamiento. Luego aplica ese mismo relleno (transform) a los datos de entrenamiento y a los de prueba, igual que se hace al normalizar o estandarizar. | H43: Alta | I43: 27/09/2026 | J43: 02_tema1_fundamentos_y_preparacion_datos.txt | K43: imputer.fit(X_train) aprende los valores de reemplazo solo con entrenamiento; imputer.transform(X_train) y imputer.transform(X_test) aplican esos mismos valores. Igual que con la normalización. | L43: imputer = SimpleImputer(strategy='mean'); imputer.fit(X_train); X_test_ok = imputer.transform(X_test). | M43: Si se calcula la media con el test incluido, el test influye en la preparación. | N43: ¿Con qué datos se calcula el valor que sustituye a los ausentes? | O43: 02 §7 (notebook datos_imputacion_seleccion).
A44: 1.8 | B44: 1. Fundamentos y preparación de datos | C44: Selección de atributos | D44: 1 | E44: 🟠 Parcial | F44: Es parte de reducir la cantidad de columnas de los datos. Se descartan las columnas poco útiles, usando un método que mide qué tan buena es cada una, ya sea sola (univariante) o junto con otras (multivariante). | G44: Practicar VarianceThreshold, f_regression y mutual_info_regression sobre datos sintéticos y iris. | H44: Media | I44: 27/09/2026 | J44: 02_tema1_fundamentos_y_preparacion_datos.txt | K44: Subtarea de la reducción de dimensionalidad (dentro de la limpieza). Necesita un algoritmo de evaluación de atributos (individual o por conjuntos) y, si es multivariante, un algoritmo de búsqueda, porque el espacio de subconjuntos crece exponencialmente (problema NP-completo). Puede ser supervisada o no. | L44: Baja varianza, F-test e información mutua del módulo sklearn.feature_selection. | M44: Un atributo con poca relación individual con la clase puede ser importante en combinación con otros. | N44: ¿Por qué hace falta un algoritmo de búsqueda en la selección multivariante? | O44: 02 §8; PDF p.28-31.
A45: 1.8.a | B45: 1. Fundamentos y preparación de datos | C45: Evaluación univariante vs. multivariante | D45: 2 | E45: 🟢 Comprendido | F45: Univariante mira cada columna por separado; multivariante mira grupos de columnas juntas. Una columna puede parecer poco útil sola, pero ser clave combinada con otras. Multivariante cuesta más cálculo, pero es más preciso. | H45: Media | I45: 27/09/2026 | J45: 02_tema1_fundamentos_y_preparacion_datos.txt | K45: Evaluación individual (univariante): mide cada atributo por separado. Evaluación de conjuntos (multivariante): mide grupos de atributos a la vez; es más costosa pero suele elegir conjuntos más relevantes en su totalidad. | L45: F-test e información mutua evalúan atributo por atributo (univariantes). | M45: La relevancia de un atributo puede depender de otros. | N45: ¿Qué ventaja tiene evaluar conjuntos de atributos frente a evaluarlos uno a uno? | O45: 02 §8; PDF p.28.
A46: 1.8.b | B46: 1. Fundamentos y preparación de datos | C46: Selección supervisada vs. no supervisada | D46: 2 | E46: 🟡 Repasar | F46: En la supervisada, se mira cada columna junto con lo que se quiere predecir (la variable objetivo), que puede servir para clasificar, para predecir números, o ambos. En la no supervisada, cada columna se analiza sin tener en cuenta la clase. | H46: Media | I46: 27/09/2026 | J46: 02_tema1_fundamentos_y_preparacion_datos.txt | K46: Selección supervisada: el atributo se analiza junto con la clase; el algoritmo de evaluación puede estar definido solo para clasificación, solo para regresión o para ambos (hay que comprobar la compatibilidad). No supervisada: se analiza el atributo sin considerar la clase. | L46: F-test (supervisada, para regresión) frente a baja varianza (no supervisada). | M46: Una técnica supervisada aprende de la clase: debe ajustarse solo con entrenamiento. | N46: ¿Qué técnica de las vistas es no supervisada? | O46: 02 §8; PDF p.28.
A47: 1.8.c | B47: 1. Fundamentos y preparación de datos | C47: Baja varianza (VarianceThreshold) | D47: 2 | E47: 🟢 Comprendido | F47: Método no supervisado: elimina las columnas cuyos valores casi no cambian, porque se asume que no ayudan a predecir. Se usa VarianceThreshold(threshold=...). La varianza mide cuánto varían los valores: S² = Σ(xi-x̄)²/(n-1). | H47: Alta | I47: 27/09/2026 | J47: 02_tema1_fundamentos_y_preparacion_datos.txt | K47: VarianceThreshold elimina atributos casi constantes: S² = suma (x_i - media)² / (n - 1); se descartan los de varianza menor que el umbral. Con datos binarios, threshold = 0,8 (1 - 0,8) = 0,16 corresponde a la varianza de Bernoulli para p = 0,8. | L47: PDF: X = [[0,0,1],[0,1,0],[1,0,0],[0,1,1],[0,1,0],[0,1,1]]; el primer atributo vale 0 en 5 de 6 filas y se descarta. Notebook: iris con threshold = 0,6. | M47: Es no supervisada: no mira si el atributo sirve para predecir la clase. | N47: ¿Por qué un atributo casi constante aporta poca información predictiva? | O47: 02 §8; PDF p.28-29 (Programa 5).
A48: 1.8.d | B48: 1. Fundamentos y preparación de datos | C48: F-test | D48: 2 | E48: 🟢 Comprendido | F48: Método supervisado que revisa una columna a la vez. Mide cuánto se relaciona una columna con la clase en línea recta (relación lineal), por eso sirve para detectar ese tipo de relación. Se usa con sklearn.feature_selection.f_regression. | H48: Alta | I48: 27/09/2026 | J48: 02_tema1_fundamentos_y_preparacion_datos.txt | K48: F-test: mide el grado de dependencia lineal entre dos atributos (aquí, atributo y clase). Clase sklearn: f_regression (módulo feature_selection). | L48: Dataset sintético: y = x1 + sin(6 pi x2) + 0,1 ruido; el F-test da su máximo en x1 (dependencia lineal) y un valor bajo en x3 (irrelevante). | M48: Solo detecta dependencia lineal: una relación sinusoidal casi no la ve. | N48: ¿Qué tipo de relación detecta el F-test? | O48: 02 §8; PDF p.29-31 (Programa 6).
A49: 1.8.e | B49: 1. Fundamentos y preparación de datos | C49: Información mutua | D49: 2 | E49: 🟢 Comprendido | F49: Método supervisado que revisa una columna a la vez. Detecta cualquier tipo de relación con la clase, sea en línea recta o no, pero necesita más ejemplos para ser confiable. Se usa con sklearn.feature_selection.mutual_info_regression. | H49: Alta | I49: 27/09/2026 | J49: 02_tema1_fundamentos_y_preparacion_datos.txt | K49: Información mutua: mide cualquier tipo de dependencia estadística, lineal o no, pero necesita más instancias para resultados fiables. Función sklearn: mutual_info_regression. | L49: En el mismo dataset sintético, la información mutua da el valor máximo en x2 (dependencia sinusoidal) y valores cercanos a 0 en x3. | M49: Con pocas instancias sus resultados son poco fiables. | N49: ¿Qué atributo del ejemplo sinusoidal detecta la información mutua y no el F-test? | O49: 02 §8; PDF p.29-31 (Programa 6).
A50: 2 | B50: 2. Validación de modelos y métricas | C50: VALIDACIÓN DE MODELOS Y MÉTRICAS DE EVALUACIÓN | D50: 0 | E50: 🟢 Comprendido | F50: Trata de cómo dividir los datos entre entrenamiento y prueba, y de evitar que el modelo aprenda de más o de menos. También cubre cómo validar y cómo medir qué tan bien funciona, en predicción de números y de categorías. Es necesario para evaluar cualquier modelo de los temas 4 y 5. | G50: Dominar k-fold y la matriz de confusión (con sus 4 métricas derivadas) antes de avanzar a los modelos de los temas 4 y 5. | H50: Alta | I50: 27/09/2026 | J50: 03_tema2_validacion_y_metricas.txt | K50: Cómo estimar el rendimiento de un modelo con casos que no usó para aprender (hold-out, validación cruzada, bootstrap), cómo ajustar hiperparámetros sin tocar el test (validación anidada) y qué métricas usar en regresión (MAE, MSE, RMSE, MAPE) y en clasificación (matriz de confusión, exactitud, precisión, sensibilidad, F1). | L50: Flujo: separar test, ajustar y comparar configuraciones con validación interna, reentrenar y medir una sola vez con el test. | M50: A partir de este capítulo el curso se centra en predicción de una clase con cuatro algoritmos: regresión lineal múltiple, KNN, regresión logística y árboles. | N50: ¿Por qué hace falta separar los datos antes de evaluar un modelo? | O50: Archivo 03 (PDF p.32-52 + notebooks de métricas y validación).
A51: 2.1 | B51: 2. Validación de modelos y métricas | C51: Introducción: entrenamiento, test, sobreajuste y subajuste | D51: 1 | E51: 🟢 Comprendido | F51: Desde el capítulo 2 se estudian 4 algoritmos: regresión lineal, KNN, regresión logística y árboles. Los datos se dividen en una parte para aprender (entrenamiento) y otra para evaluar con ejemplos nunca vistos (test). Esa división es la base de toda validación. | G51: Distinguir claramente overfitting de underfitting con un ejemplo propio antes de pasar a hold-out. | H51: Alta | I51: 27/09/2026 | J51: 03_tema2_validacion_y_metricas.txt | K51: Conjunto de entrenamiento = datos con los que el algoritmo aprende su modelo. Conjunto de test = datos que el modelo no ha visto y con los que se mide la generalización; no debe contener instancias del entrenamiento. Objetivo: la complejidad que minimiza el error de generalización. | L51: Un modelo que acierta 100 % lo ya visto y 60 % lo nuevo está sobreajustado. | M51: Los dos errores (entrenamiento y generalización) deben mirarse juntos. | N51: ¿Qué dos errores compararías para detectar sobreajuste? | O51: 03 §0; PDF p.32-35.
A52: 2.1.a | B52: 2. Validación de modelos y métricas | C52: Conjunto de entrenamiento y conjunto de test | D52: 2 | E52: 🟢 Comprendido | F52: El entrenamiento son los datos con los que el algoritmo aprende. El test son datos que nunca vio y que se usan solo para evaluar. Así la nota es honesta, por eso el test no puede incluir ningún ejemplo del entrenamiento. | H52: Alta | I52: 27/09/2026 | J52: 03_tema2_validacion_y_metricas.txt | K52: Entrenamiento (training): datos que el algoritmo usa para aprender su modelo de conocimiento. Test: datos sobre los que el algoritmo predice sin haberlos visto en el entrenamiento; ninguna instancia de entrenamiento puede estar en el test. | L52: X_train, X_test, y_train, y_test = train_test_split(X, y, test_size=0.3, random_state=0). | M52: Los errores de entrenamiento son los cometidos al predecir los mismos ejemplos con que se entrenó; los de generalización, los del test. | N52: ¿Por qué el test no puede contener ninguna instancia del entrenamiento? | O52: 03 §0; PDF p.33; glosario PDF p.96.
A53: 2.1.b | B53: 2. Validación de modelos y métricas | C53: Sobreajuste (overfitting) | D53: 2 | E53: 🟢 Comprendido | F53: El modelo 'memoriza' los datos de entrenamiento en vez de aprender la idea general. Por eso casi no se equivoca con ellos, pero se equivoca mucho con datos nuevos (el error en test es alto). | H53: Alta | I53: 27/09/2026 | J53: 03_tema2_validacion_y_metricas.txt | K53: Sobreajuste (overfitting): el modelo aprende de memoria el entrenamiento; errores de entrenamiento muy bajos y errores de generalización altos. Se asocia a modelos de complejidad elevada. | L53: Árbol sin límite de profundidad: acierta todo el entrenamiento y falla en datos nuevos. | M53: Una diferencia entre entrenamiento y test sugiere sobreajuste, pero también puede deberse a azar o a un cambio de población. | N53: ¿Qué patrón de errores indica sobreajuste? | O53: 03 §0; PDF p.33-34; glosario PDF p.97.
A54: 2.1.c | B54: 2. Validación de modelos y métricas | C54: Subajuste (underfitting) | D54: 2 | E54: 🟢 Comprendido | F54: El modelo aprende una idea demasiado general y simple. Por eso se equivoca bastante tanto con los datos de entrenamiento como con los de test, y esos errores son parecidos entre sí. | H54: Alta | I54: 27/09/2026 | J54: 03_tema2_validacion_y_metricas.txt | K54: Subajuste (underfitting): el modelo aprende un concepto demasiado general o simple; errores de entrenamiento y de generalización altos y parecidos entre sí. | L54: Ajustar una recta a datos claramente curvos. | M54: Puede deberse a un modelo demasiado limitado o a atributos sin suficiente señal. | N54: ¿Cómo se ven los errores de entrenamiento y test en un modelo subajustado? | O54: 03 §0; PDF p.33-34; glosario PDF p.97.
A55: 2.1.d | B55: 2. Validación de modelos y métricas | C55: Compromiso sesgo-varianza (bias-variance tradeoff) | D55: 2 | E55: 🟢 Comprendido | F55: Un modelo demasiado simple (sesgo alto) no logra ajustarse ni al entrenamiento: es el subajuste. Uno demasiado sensible (varianza alta) encaja muy bien el entrenamiento pero falla con datos nuevos: es el sobreajuste. La nota de entrenamiento siempre supera a la de validación. El mejor modelo tiene complejidad intermedia. | H55: Media | I55: 27/09/2026 | J55: 03_tema2_validacion_y_metricas.txt | K55: Sesgo alto = subajuste (no ajusta ni el entrenamiento); varianza alta = sobreajuste (ajusta muy bien el entrenamiento y falla con datos nuevos). El puntaje de entrenamiento siempre supera al de validación; con complejidad muy baja ambos son malos, con muy alta el de validación cae, y existe un punto intermedio óptimo. | L55: Curva de validación del polinomio: el equilibrio óptimo del notebook está en grado 3. | M55: Más complejidad no es siempre mejor. | N55: ¿Qué ocurre con el puntaje de validación cuando la complejidad es demasiado alta? | O55: 03 §0 (notebook validacion_modelos, sección 1.3).
A56: 2.1.e | B56: 2. Validación de modelos y métricas | C56: Validación (definición general) y métricas base | D56: 2 | E56: 🟢 Comprendido | F56: Validar es dividir los datos en entrenamiento y test para evaluar bien los algoritmos. Se presentan dos medidas base: MAE para predecir números (error promedio) y exactitud (accuracy) para categorías (porcentaje de aciertos). MAE = (1/n)·Σ|y_i - ŷ_i|; Exactitud(%) = 100·(1/n)·Σ[y_i = ŷ_i]. | H56: Media | I56: 27/09/2026 | J56: 03_tema2_validacion_y_metricas.txt | K56: Validación (validation o resampling): dividir los datos en subconjuntos de entrenamiento y test para evaluar bien los algoritmos. Métricas base: MAE = (1/n) suma abs(y_i - yhat_i) para regresión; Exactitud (%) = 100 (1/n) suma [y_i = yhat_i] para clasificación (el corchete vale 1 si coinciden y 0 si no). | L56: Con y = [10,20,30] y predicciones [12,18,24]: MAE = (2+2+6)/3 = 3,33. | M56: MAE y exactitud se detallan en 2.5 y 2.6. | N56: ¿Qué mide la exactitud y qué mide el MAE? | O56: 03 §0; PDF p.34-35.
A57: 2.2 | B57: 2. Validación de modelos y métricas | C57: Validación hold-out | D57: 1 | E57: 🟢 Comprendido | F57: Consiste en separar los datos en dos partes, entrenamiento y test, una sola vez. Un reparto habitual es 66/34 o 70/30, es decir, más o menos dos tercios para aprender y el resto para evaluar. | G57: Reproducir el Programa 7 (iris + DummyClassifier) a mano para fijar train_test_split. | H57: Alta | I57: 27/09/2026 | J57: 03_tema2_validacion_y_metricas.txt | K57: Hold-out: se divide el conjunto de datos una sola vez en entrenamiento y test. Reparto habitual 66 % y 34 %, o 70 % y 30 %. | L57: Iris: 150 instancias, test_size=0.3 da 105 de entrenamiento y 45 de test. | M57: Con un único test, su elección puede variar mucho las métricas (poca representatividad). | N57: ¿Por qué una sola división puede dar una nota engañosa? | O57: 03 §1; PDF p.35-38.
A58: 2.2.a | B58: 2. Validación de modelos y métricas | C58: Hold-out no aleatorio | D58: 2 | E58: 🟢 Comprendido | F58: Se toma el primer porcentaje de las muestras, en su orden original, para entrenar y el resto para test. Sirve cuando el orden importa porque unas muestras dependen de otras, como en series temporales (datos medidos a lo largo del tiempo). | H58: Media | I58: 27/09/2026 | J58: 03_tema2_validacion_y_metricas.txt | K58: Hold-out no aleatorio: el primer X % de las muestras (en su orden original) es entrenamiento y el resto es test. Útil cuando hay dependencias entre muestras, p. ej. series temporales. | L58: Entrenar con los primeros 8 años y evaluar con los 2 últimos años de una serie. | M58: Mezclar al azar una serie temporal haría que el entrenamiento viera el futuro del test. | N58: ¿Por qué en series temporales no se baraja antes de cortar? | O58: 03 §1; PDF p.35.
A59: 2.2.b | B59: 2. Validación de modelos y métricas | C59: Hold-out aleatorio | D59: 2 | E59: 🟢 Comprendido | F59: Primero se mezclan las muestras al azar y luego se corta entre entrenamiento y test. Se recomienda cuando el orden de las muestras no importa, porque ninguna muestra depende de otra. | H59: Media | I59: 27/09/2026 | J59: 03_tema2_validacion_y_metricas.txt | K59: Hold-out aleatorio: primero se reordenan aleatoriamente las muestras y luego se hace el corte. Recomendable si no hay dependencias de orden que respetar. | L59: train_test_split baraja por defecto; con shuffle=False se conserva el orden. | M59: Fija random_state para poder repetir el mismo reparto. | N59: ¿Cuándo es adecuado barajar antes de partir? | O59: 03 §1; PDF p.35-36.
A60: 2.2.c | B60: 2. Validación de modelos y métricas | C60: train_test_split (código real) | D60: 2 | E60: 🟢 Comprendido | F60: Es la función de sklearn que reparte los datos en entrenamiento y test. test_size indica qué proporción va a test, random_state fija la semilla del azar para repetir el mismo reparto, y shuffle=False mantiene el orden original. X_train, X_test, y_train, y_test = train_test_split(X, y, test_size=0.3, random_state=0). | H60: Alta | I60: 27/09/2026 | J60: 03_tema2_validacion_y_metricas.txt | K60: train_test_split(X, y, test_size, random_state) devuelve X_train, X_test, y_train, y_test. test_size = proporción de test; random_state = semilla de la reordenación previa; shuffle=False evita reordenar. Sin test_size, sklearn usa 0,25. DummyClassifier predice al azar según la frecuencia de clases; clf.score(X_test, y_test) devuelve la exactitud. | L60: Programa 7: iris con DummyClassifier da Training 105, Test 45 y exactitud 0,3111 (tres clases balanceadas, azar cercano a 1/3). | M60: Notebook de métricas: sus celdas de hold-out sobre California housing están vacías como ejercicio guiado. | N60: ¿Qué hace el parámetro random_state? | O60: 03 §1; PDF p.36-38 (Programa 7); notebook validacion_modelos celda 11.
A61: 2.2.d | B61: 2. Validación de modelos y métricas | C61: Partición train/test fijada por el problema | D61: 2 | E61: 🟢 Comprendido | F61: A veces el problema ya trae la división hecha, por ejemplo para comparar con resultados de otros trabajos. Esto también cuenta como una forma de hold-out, es decir, una sola división entre entrenamiento y test. | H61: Baja | I61: 27/09/2026 | J61: 03_tema2_validacion_y_metricas.txt | K61: La partición train y test puede venir fijada por el propio problema (para comparar con resultados de otros trabajos); también se considera una forma de hold-out. | L61: Un concurso que publica los conjuntos de entrenamiento y de test ya separados. | M61: Si el test viene dado, no se vuelve a repartir. | N61: ¿Por qué se respeta una partición fijada por el problema? | O61: 03 §1; PDF p.36.
A62: 2.3 | B62: 2. Validación de modelos y métricas | C62: Validación cruzada / K-fold | D62: 1 | E62: 🟢 Comprendido | F62: Con una sola división, el resultado puede depender de la suerte del reparto. Para corregirlo, se parten los datos en K bolsas (folds) del mismo tamaño. Se repite la prueba K veces, y cada vez una bolsa distinta sirve de test. | G62: Ejecutar mentalmente el ejemplo KFold(n_splits=3) sobre 10 elementos para ver por qué las bolsas no quedan exactamente iguales. | H62: Alta | I62: 27/09/2026 | J62: 03_tema2_validacion_y_metricas.txt | K62: Validación cruzada (CV): se parte el conjunto en K subconjuntos de igual tamaño (bolsas o folds) y se hacen K validaciones tipo hold-out, usando cada bolsa una vez como test y el resto como entrenamiento. Se resumen las K notas (media y desviación). Recomendable repetirla varias veces si K < n, y K = 10 es un estándar práctico para datasets grandes. | L62: Iris, K = 10: cada bolsa tiene 15 ejemplos. | M62: Cada vuelta construye un modelo distinto: no es el mismo modelo evaluado K veces. | N62: ¿Por qué el resumen de K notas informa mejor que una sola? | O62: 03 §2; PDF p.38-41.
A63: 2.3.a | B63: 2. Validación de modelos y métricas | C63: K bolsas (folds) | D63: 2 | E63: 🟢 Comprendido | F63: Los datos se dividen en K bolsas de unos n/K ejemplos cada una. En cada una de las K vueltas, una bolsa distinta es el test y las demás son el entrenamiento. Ejemplo: 150 ejemplos (iris) con K=10 dan bolsas de 15 ejemplos. | H63: Alta | I63: 27/09/2026 | J63: 03_tema2_validacion_y_metricas.txt | K63: K bolsas de unos n/K ejemplos cada una; en cada una de las K vueltas una bolsa distinta es test y las demás entrenamiento. Si n no es divisible entre K, las bolsas no quedan iguales. | L63: Programa 8: 10 elementos y KFold(n_splits=3): bolsas de test de 4, 3 y 3 elementos. | M63: Cada ejemplo sirve como test exactamente una vez. | N63: ¿Por qué con 10 elementos y K = 3 la primera bolsa tiene 4 elementos? | O63: 03 §2; PDF p.38-40 (Programa 8).
A64: 2.3.b | B64: 2. Validación de modelos y métricas | C64: Leave-one-out | D64: 2 | E64: 🟢 Comprendido | F64: Es una validación cruzada: se aparta un solo dato para probar y se entrena con todos los demás. Se repite hasta que cada dato haya sido la prueba una vez; con n datos son n entrenamientos, por eso sale caro con muchos datos. | H64: Media | I64: 27/09/2026 | J64: 03_tema2_validacion_y_metricas.txt | K64: Leave-one-out: caso particular K = n; se predice cada ejemplo con todos los demás como entrenamiento. Ventaja: no hay aleatoriedad en las bolsas. Desventaja: coste alto (n entrenamientos y n predicciones frente a K entrenamientos y n predicciones); impracticable con millones de instancias. | L64: Con 150 instancias hay 150 entrenamientos. | M64: Con datasets muy grandes se usa K = 10 o similar. | N64: ¿Cuántos entrenamientos exige leave-one-out con n instancias? | O64: 03 §2; PDF p.40-41; glosario PDF p.98.
A65: 2.3.c | B65: 2. Validación de modelos y métricas | C65: Validación estratificada | D65: 2 | E65: 🟢 Comprendido | F65: Al dividir los datos, cada categoría queda con casi la misma proporción en entrenamiento y en prueba. Así, si una categoría es rara, no desaparece de la prueba y la nota no sale sesgada. | H65: Media | I65: 27/09/2026 | J65: 03_tema2_validacion_y_metricas.txt | K65: Validación estratificada: los conjuntos de test mantienen aproximadamente la misma distribución de clases que el de entrenamiento; evita el problema del desbalanceo de clases. El PDF solo la menciona (enlace externo). | L65: Con 90 % de una clase y 10 % de otra, cada bolsa conserva esa proporción. | M65: El curso no desarrolla su implementación. | N65: ¿Qué proporción conserva cada bolsa en una validación estratificada? | O65: 03 §2; PDF p.41; glosario PDF p.98.
A66: 2.3.d | B66: 2. Validación de modelos y métricas | C66: cross_val_score / KFold (código real) | D66: 2 | E66: ⚪ Pendiente | F66: Es la instrucción de la librería que prueba un modelo varias veces con distintos trozos de los datos. Devuelve un porcentaje de aciertos por cada trozo. Luego se resumen con el promedio y cuánto varían, para saber qué tan estable es el modelo. | H66: Alta | I66: 27/09/2026 | J66: 03_tema2_validacion_y_metricas.txt | K66: cross_val_score(clf, X, y, cv=KFold(n_splits=10)) devuelve un arreglo con K exactitudes (una por bolsa) que se resume con media y desviación. cross_val_predict devuelve un único vector con la predicción de cada ejemplo cuando su bolsa fue test. | L66: Programa 9 (iris + DummyClassifier, K = 10): exactitud 0,307 con desviación 0,144. | M66: Con KFold(shuffle=True) las bolsas son aleatorias. | N66: ¿Qué devuelve cross_val_score? | O66: 03 §2; PDF p.40-41 (Programa 9); notebook validacion_modelos celda 12.
A67: 2.3.e | B67: 2. Validación de modelos y métricas | C67: Bootstrapping / out-of-bag (OOB) | D67: 2 | E67: ⚪ Pendiente | F67: Es otra forma de dividir los datos: se sacan ejemplos al azar, pudiendo repetirlos, para entrenar. Los que no salieron sirven de prueba y se llaman 'out of bag' (fuera de la bolsa). Así ningún ejemplo queda a la vez en entrenamiento y prueba. | H67: Media | I67: 27/09/2026 | J67: 03_tema2_validacion_y_metricas.txt | K67: Bootstrapping (solo notebook): se fija un tamaño de muestra y se eligen instancias con reemplazo; una instancia puede repetirse en el entrenamiento. Las no elegidas son el test y se llaman out of bag (OOB). Nunca hay instancias repetidas entre entrenamiento y test. | L67: resample(data, replace=True, n_samples=5, random_state=3); oob = [x for x in data if x not in boot]. Repetido 40 veces con ElasticNet da una distribución del MAE. | M67: No es lo mismo que la partición en bolsas sin repetición de K-fold. | N67: ¿Por qué un caso puede aparecer dos veces en una muestra bootstrap? | O67: 03 §2-bis (notebook validacion_modelos, sección 1.2).
A68: 2.4 | B68: 2. Validación de modelos y métricas | C68: Ajuste de parámetros y validación anidada | D68: 1 | E68: ⚪ Pendiente | F68: Los algoritmos tienen ajustes que elige la persona antes de entrenar (como perillas). Aquí se busca la mejor combinación sin usar nunca los datos de prueba. Así esos datos siguen mostrando cómo funcionará el modelo con casos nuevos. | G68: Explicar con palabras propias por qué el test debe quedar aislado del ajuste antes de ver validación anidada. | H68: Alta | I68: 27/09/2026 | J68: 03_tema2_validacion_y_metricas.txt | K68: Los algoritmos tienen parámetros de configuración (hiperparámetros) que afectan la bondad; encontrar su elección óptima es el ajuste de parámetros (hyperparameter tuning), una búsqueda que maximiza una métrica (exactitud, MAE...). Regla: nunca se ajusta maximizando la bondad sobre el test. | L68: Elegir el número de vecinos k comparando varias configuraciones con validación interna. | M68: El PDF no incluye código de este apartado. | N68: ¿Por qué el test debe permanecer aislado durante el ajuste? | O68: 03 §3; PDF p.42-44.
A69: 2.4.a | B69: 2. Validación de modelos y métricas | C69: Regla: el test nunca se usa para ajustar parámetros | D69: 2 | E69: ⚪ Pendiente | F69: No se deben ajustar los parámetros buscando el mejor resultado en los datos de prueba. Esos datos deben quedar aislados todo el tiempo. Si no, el modelo se adapta a ellos y su resultado parece mejor de lo que realmente es. | H69: Alta | I69: 27/09/2026 | J69: 03_tema2_validacion_y_metricas.txt | K69: El ajuste de parámetros no debe hacerse maximizando la bondad sobre el conjunto de test: el test debe permanecer aislado durante todo el entrenamiento y el ajuste, para evitar el sobreajuste y evaluar la capacidad de generalización. | L69: Si eliges la configuración que mejor puntúa en el test, ese test deja de ser una prueba independiente. | M69: La mejor nota entre muchas configuraciones tiende a ser optimista. | N69: ¿Por qué elegir la mejor configuración según el test lo contamina? | O69: 03 §3; PDF p.43.
A70: 2.4.b | B70: 2. Validación de modelos y métricas | C70: Test de validación (validation test) | D70: 2 | E70: ⚪ Pendiente | F70: Es un grupo de datos apartado del propio entrenamiento, usado para comparar distintas configuraciones del modelo sin tocar la prueba real. Así el modelo final se evalúa una sola vez con la prueba independiente, y el resultado es honesto. | H70: Alta | I70: 27/09/2026 | J70: 03_tema2_validacion_y_metricas.txt | K70: Test de validación: conjunto extraído del entrenamiento. Cada configuración se entrena con el entrenamiento y se prueba con el test de validación; tras hallar la mejor configuración, el modelo final se evalúa una sola vez con el test independiente. | L70: Separar 20 % del entrenamiento como validación para comparar profundidades de árbol. | M70: Un único test de validación también puede sobreajustarse a sus peculiaridades. | N70: ¿Con qué datos se evalúa el modelo final? | O70: 03 §3; PDF p.43.
A71: 2.4.c | B71: 2. Validación de modelos y métricas | C71: Validación anidada (nested validation) | D71: 2 | E71: ⚪ Pendiente | F71: Usa dos niveles de prueba. Afuera, la división original entre entrenamiento y prueba. Adentro, varias pruebas dentro del entrenamiento para elegir los mejores ajustes. Luego se reentrena con todo el entrenamiento y se evalúa una sola vez con la prueba independiente. | H71: Alta | I71: 27/09/2026 | J71: 03_tema2_validacion_y_metricas.txt | K71: Validación anidada (nested o double validation): dos niveles. Externa: la partición original en entrenamiento y test. Interna: validación cruzada dentro del entrenamiento para ajustar parámetros, buscando el promedio máximo de bondad en los tests internos. Luego se reentrena con todo el entrenamiento con los parámetros óptimos y se evalúa en el test independiente. | L71: Exterior: entrenamiento y test; interior: 5-fold sobre el entrenamiento para elegir la profundidad. | M71: Toda transformación aprendida de los datos se ajusta dentro de cada entrenamiento interno. | N71: ¿Qué parte de los datos no participa nunca en la elección de parámetros? | O71: 03 §3; PDF p.44.
A72: 2.4.d | B72: 2. Validación de modelos y métricas | C72: Curvas de validación y de aprendizaje | D72: 2 | E72: ⚪ Pendiente | F72: Son dos gráficos que comparan el desempeño en entrenamiento y en validación (datos apartados para comprobar). Uno cambia un ajuste del modelo, como el grado de un polinomio. El otro cambia la cantidad de datos de entrenamiento, con el ajuste fijo. | H72: Media | I72: 27/09/2026 | J72: 03_tema2_validacion_y_metricas.txt | K72: Curva de validación (validation_curve): puntaje de entrenamiento y de validación al variar un hiperparámetro (p. ej. grado 0 a 20 con cv=7). Curva de aprendizaje (learning_curve): lo mismo al variar el tamaño del entrenamiento con el hiperparámetro fijo. | L72: El notebook concluye que el equilibrio óptimo del polinomio está en grado 3. | M72: Son gráficos de diagnóstico, no un método de ajuste automático. | N72: ¿Qué se varía en una curva de validación y qué en una curva de aprendizaje? | O72: 03 §3 (notebook validacion_modelos, celdas 40-49).
A73: 2.5 | B73: 2. Validación de modelos y métricas | C73: Evaluación en regresión: MAE, MSE, RMSE, MAPE | D73: 1 | E73: ⚪ Pendiente | F73: Son formas de medir qué tan lejos quedan las predicciones numéricas de los valores reales. MAE y RMSE se expresan en la misma unidad de lo que se predice. MAPE lo expresa en porcentaje, es decir, relativo al valor real. | G73: Construir una tabla de variables comparando MAE/MSE/RMSE/MAPE antes de memorizar fórmulas sueltas. | H73: Alta | I73: 27/09/2026 | J73: 03_tema2_validacion_y_metricas.txt | K73: Métricas absolutas (misma unidad que la clase): MAE y RMSE. Métrica relativa: MAPE (porcentaje). MSE aparece en el notebook como RMSE al cuadrado. Las métricas de error actúan como función de coste: entrenar es hallar parámetros que la minimicen. | L73: Reales [10,20,30], predicciones [12,18,24], errores [-2,2,6]: MAE 3,33; MSE 14,67; RMSE 3,83; MAPE 16,67 %. | M73: R2 no se define en este capítulo del curso: aparece en el archivo 05 (regresión lineal). | N73: ¿Qué métrica penaliza más un error aislado muy grande? | O73: 03 §4; PDF p.44-47.
A74: 2.5.a | B74: 2. Validación de modelos y métricas | C74: MAE (error absoluto medio) | D74: 2 | E74: ⚪ Pendiente | F74: Es el promedio de cuánto se equivoca el modelo, sin importar si se pasa o se queda corto. Se expresa en la misma unidad de lo que se predice, por lo que es fácil de interpretar. | H74: Alta | I74: 27/09/2026 | J74: 03_tema2_validacion_y_metricas.txt | K74: MAE = (1/n) suma abs(y_i - yhat_i). Métrica absoluta: se expresa en la unidad de la clase. | L74: Errores [-2, 2, 6]: MAE = (2+2+6)/3 = 3,33. | M74: Trata cada error proporcionalmente a su tamaño. | N74: Dos pares de errores [10,10] y [0,20], ¿tienen el mismo MAE? | O74: 03 §0 y §4; PDF p.34-35.
A75: 2.5.b | B75: 2. Validación de modelos y métricas | C75: MSE (error cuadrático medio) | D75: 2 | E75: ⚪ Pendiente | F75: Se calcula el error de cada predicción, se eleva al cuadrado y se promedia. Es lo mismo que el RMSE antes de sacar la raíz. Sirve para medir qué tan lejos quedan las predicciones de los valores reales. | H75: Media | I75: 27/09/2026 | J75: 03_tema2_validacion_y_metricas.txt | K75: MSE = (1/m) suma (yhat_i - y_i)^2 (notebook). Es el RMSE sin la raíz; unidades al cuadrado. | L75: Errores [-2, 2, 6]: MSE = (4+4+36)/3 = 14,67. | M75: Un error grande pesa mucho más por el cuadrado. | N75: ¿Qué relación hay entre MSE y RMSE? | O75: 03 §4 (notebook métricas, sección 1.1).
A76: 2.5.c | B76: 2. Validación de modelos y métricas | C76: RMSE (raíz del error cuadrático medio) | D76: 2 | E76: ⚪ Pendiente | F76: Es parecido al MAE, pero cada error se eleva al cuadrado antes de promediar y al final se saca la raíz. Por eso los errores grandes pesan mucho más. Sirve cuando equivocarse por mucho es especialmente grave. | H76: Alta | I76: 27/09/2026 | J76: 03_tema2_validacion_y_metricas.txt | K76: RMSE = raíz cuadrada de (1/n) suma (y_i - yhat_i)^2. Los errores grandes pesan más. Se expresa en la unidad de la clase. | L76: MSE 14,67 da RMSE de aproximadamente 3,83. Errores [10,10] y [0,20]: mismo MAE (10), RMSE 10 frente a 14,14. | M76: El RMSE no es la media de los errores absolutos: la raíz se aplica después de promediar los cuadrados. | N76: ¿Por qué [10,10] y [0,20] tienen distinto RMSE con el mismo MAE? | O76: 03 §4; PDF p.44-45.
A77: 2.5.d | B77: 2. Validación de modelos y métricas | C77: MAPE (error porcentual absoluto medio) | D77: 2 | E77: ⚪ Pendiente | F77: Mide el error como porcentaje del valor real. Sirve para comparar errores en cosas de tamaños muy distintos, por ejemplo precios pequeños y grandes, porque el porcentaje no depende de la escala. | H77: Media | I77: 27/09/2026 | J77: 03_tema2_validacion_y_metricas.txt | K77: MAPE (%) = 100 (1/n) suma abs(y_i - yhat_i) / y_i. Versión del notebook con protección: (1/m) suma abs(yhat_i - y_i) / max(epsilon, abs(y_i)). Es una métrica relativa. | L77: Proporciones 2/10, 2/20 y 6/30: promedio 16,67 %. | M77: Si el valor real vale 0 la fórmula directa no está definida. | N77: ¿Qué hace el notebook para evitar dividir entre cero en el MAPE? | O77: 03 §4; PDF p.45-46; notebook métricas.
A78: 2.5.e | B78: 2. Validación de modelos y métricas | C78: make_scorer y greater_is_better | D78: 2 | E78: ⚪ Pendiente | F78: La librería sklearn supone que un número mayor es mejor. Pero RMSE y MAPE son errores: menos es mejor. Por eso, al crear la métrica con make_scorer(), se indica greater_is_better=False. cross_validate() permite medir varias métricas a la vez. | H78: Media | I78: 27/09/2026 | J78: 03_tema2_validacion_y_metricas.txt | K78: sklearn asume que mayor es mejor; RMSE y MAPE son errores (menor es mejor), por eso make_scorer(funcion, greater_is_better=False). MAE ya existe como 'neg_mean_absolute_error'. cross_validate admite varias métricas a la vez en scoring y devuelve fit_time, score_time y test_ y train_ de cada métrica (8 entradas con MAE, MAPE y RMSE). | L78: metricas = {'MAE': 'neg_mean_absolute_error', 'RMSE': make_scorer(lambda y, yp: sqrt(mean_squared_error(y, yp)), greater_is_better=False)}. | M78: Los valores salen negativos porque sklearn invierte el signo de los errores. | N78: ¿Por qué se pasa greater_is_better=False en RMSE? | O78: 03 §4; PDF p.46-47 (Programa 10).
A79: 2.6 | B79: 2. Validación de modelos y métricas | C79: Evaluación en clasificación: matriz de confusión, precisión, sensibilidad, F1, accuracy | D79: 1 | E79: ⚪ Pendiente | F79: Para evaluar una clasificación, primero cuenta qué categorías acertó y cuáles confundió. La matriz de confusión separa esos casos. De ella salen la exactitud, la precisión, la sensibilidad y F1; cada medida responde una pregunta distinta. | G79: Practicar leyendo una matriz de confusión 2x2 y derivando TP/TN/FP/FN antes de calcular precisión/recall/F1. | H79: Alta | I79: 27/09/2026 | J79: 03_tema2_validacion_y_metricas.txt | K79: En clasificación solo importa acertar o no la clase. La métrica principal es la matriz de confusión; de ella salen exactitud, precisión, sensibilidad (recall) y F1. Elegir qué clase es la positiva cambia precisión, recall y F1. | L79: Fraude (positivo): TP 8, FN 2, FP 12, TN 78 sobre 100 compras. | M79: Una nota general puede ocultar el error que más cuesta. | N79: ¿Por qué hay que decidir primero qué clase llamas positiva? | O79: 03 §5; PDF p.47-52.
A80: 2.6.a | B80: 2. Validación de modelos y métricas | C80: Matriz de confusión | D80: 2 | E80: ⚪ Pendiente | F80: Es una tabla con tantas filas y columnas como categorías. Cada celda cuenta cuántos casos de una categoría real el modelo asignó a una categoría predicha. Los aciertos son la suma de la diagonal; los fallos, el resto del total. | H80: Alta | I80: 27/09/2026 | J80: 03_tema2_validacion_y_metricas.txt | K80: Matriz de confusión: cuadrada de orden m (número de clases); P_ij = número de predicciones con clase real C_i y predicha C_j. Aciertos = suma de la diagonal; fallos = n - suma de la diagonal. Filas = clase real; columnas = clase predicha. | L80: Iris, DummyClassifier: [[17,16,17],[15,16,19],[18,22,10]]; diagonal 17+16+10 = 43 aciertos de 150, exactitud 0,287. | M80: En multiclase se puede evaluar cada clase contra el resto, con m matrices. | N80: ¿Cómo se calculan los aciertos a partir de la matriz? | O80: 03 §5; PDF p.47-49; glosario PDF p.96.
A81: 2.6.b | B81: 2. Validación de modelos y métricas | C81: TP / TN / FP / FN (caso binario) | D81: 2 | E81: ⚪ Pendiente | F81: Son los cuatro resultados posibles cuando hay dos opciones, 'sí' o 'no'. TP: dijo 'sí' y era 'sí'. TN: dijo 'no' y era 'no'. FP: dijo 'sí' pero era 'no'. FN: dijo 'no' pero era 'sí'. De aquí salen precisión, sensibilidad y F1. | H81: Alta | I81: 27/09/2026 | J81: 03_tema2_validacion_y_metricas.txt | K81: TP: el modelo dice sí y la realidad es sí. TN: dice no y es no. FP: dice sí y es no. FN: dice no y es sí. Tabla: real positiva - predicha positiva TP, predicha negativa FN; real negativa - predicha positiva FP, predicha negativa TN. | L81: Test médico: FP = sano marcado como enfermo (pruebas extra); FN = enfermo marcado como sano (riesgo grave). | M81: FP y FN no son el mismo error ni cuestan lo mismo. | N81: ¿Por qué un falso negativo en un test de cáncer suele ser más grave? | O81: 03 §5; PDF p.49 (Tabla 6); notebook métricas sección 1.2.1.
A82: 2.6.c | B82: 2. Validación de modelos y métricas | C82: Exactitud (accuracy) | D82: 2 | E82: ⚪ Pendiente | F82: Es el porcentaje de predicciones correctas sobre el total. Es fácil de entender, pero puede engañar cuando una categoría es mucho más frecuente que las otras, porque acertar la común ya da un número alto. | H82: Alta | I82: 27/09/2026 | J82: 03_tema2_validacion_y_metricas.txt | K82: Exactitud (%) = 100 (TP + TN) / (TP + TN + FP + FN); en general 100 suma P_ii / n. Por clase: Exactitud(C_i) = 100 P_ii / suma_j P_ij. | L82: TP 8, TN 78, FP 12, FN 2: exactitud = 86 %. | M82: Puede engañar con clases desbalanceadas. | N82: Con 10 fraudes en 100, ¿qué exactitud logra un sistema que siempre dice legítima? | O82: 03 §5; PDF p.48-49.
A83: 2.6.d | B83: 2. Validación de modelos y métricas | C83: Precisión | D83: 2 | E83: ⚪ Pendiente | F83: De todos los casos que el modelo marcó como 'sí', indica qué proporción realmente lo era. Sirve para saber cuánta confianza dar cuando el modelo dice 'sí'. | H83: Alta | I83: 27/09/2026 | J83: 03_tema2_validacion_y_metricas.txt | K83: Precisión (%) = 100 TP / (TP + FP): proporción de aciertos entre todas las predicciones positivas. Mide cuánto se puede confiar cuando el modelo dice sí. Interesa cuando importa limitar los falsos positivos. | L83: TP 8, FP 12: precisión = 8/20 = 40 %. | M83: Una precisión de 100 % (FP = 0) no implica detectar todos los positivos reales. | N83: ¿Qué indica una precisión del 40 %? | O83: 03 §5; PDF p.49-50.
A84: 2.6.e | B84: 2. Validación de modelos y métricas | C84: Sensibilidad / Recall / Exhaustividad | D84: 2 | E84: ⚪ Pendiente | F84: De todos los casos que realmente eran 'sí', indica qué proporción detectó el modelo. Sirve para saber si se le están escapando casos positivos reales, es decir, falsos negativos. | H84: Alta | I84: 27/09/2026 | J84: 03_tema2_validacion_y_metricas.txt | K84: Sensibilidad (recall, exhaustividad, cobertura) (%) = 100 TP / (TP + FN): proporción de positivos reales que el modelo detecta. Interesa cuando importa evitar falsos negativos. | L84: TP 8, FN 2: sensibilidad = 8/10 = 80 %. | M84: Una sensibilidad de 100 % (FN = 0) es compatible con muchos falsos positivos (por ejemplo, decir sí siempre). | N84: ¿Qué proporción de fraudes se detecta si TP = 8 y FN = 2? | O84: 03 §5; PDF p.50.
A85: 2.6.f | B85: 2. Validación de modelos y métricas | C85: F1-score | D85: 2 | E85: ⚪ Pendiente | F85: Es un solo número que combina precisión y sensibilidad. Es útil porque a veces mejorar una empeora la otra. Es un promedio especial que baja bastante si alguna de las dos es mala. | H85: Alta | I85: 27/09/2026 | J85: 03_tema2_validacion_y_metricas.txt | K85: F1 = 100 (2 sensibilidad precisión) / (sensibilidad + precisión): media armónica de ambas; baja si alguna es baja. Mejor métrica que la exactitud con datos desbalanceados. En multiclase se usa average='micro' en el curso. | L85: Precisión 0,40 y sensibilidad 0,80: F1 = 2 (0,40 0,80) / 1,20 = 0,533. | M85: No decide por ti cuánto cuesta cada tipo de error. | N85: ¿Por qué F1 usa una media armónica y no una aritmética? | O85: 03 §5; PDF p.50 (Programa 11); notebook métricas sección 1.2.4.
A86: 2.6.g | B86: 2. Validación de modelos y métricas | C86: Datos no balanceados: por qué accuracy engaña | D86: 2 | E86: ⚪ Pendiente | F86: Si una categoría es nueve veces más común que otra, un modelo que siempre responde la más común acierta más del 80% sin haber aprendido nada. Por eso, en estos casos, se necesitan también precisión, sensibilidad y F1. | H86: Media | I86: 27/09/2026 | J86: 03_tema2_validacion_y_metricas.txt | K86: Notebook (digits, el dígito 9 contra el resto, razón 9 a 1): un DummyClassifier que siempre dice no es 9 supera 80 % de exactitud sin haber aprendido nada, similar a un SVM real; por eso hacen falta precisión, recall y F1. | L86: DummyClassifier(strategy='most_frequent').fit(X_train, y_train).score(X_test, y_test). | M86: La curva ROC y el AUC no aparecen en el capítulo 2 del curso (sí en el de regresión logística, 5.1.l). | N86: ¿Por qué acertar 90 de 100 puede ser inútil si buscas fraudes? | O86: 03 §5 (notebook métricas, sección 1.2.2).
A87: 3 | B87: 3. Extracción de características | C87: EXTRACCIÓN DE CARACTERÍSTICAS (VARIABLES E IMÁGENES) | D87: 0 | E87: ⚪ Pendiente | F87: Este bloque enseña a describir variables y trabajar con imágenes: cambiar su aspecto, separar el objeto del fondo y medir forma o textura. La teoría está en el PowerPoint del profesor (carpeta CLASES); el manual PDF no cubre este tema. | G87: Empezar por variables cuantitativas y 'la imagen como dato' antes de los descriptores de forma y textura. | H87: Alta | I87: 27/09/2026 | J87: resumen_tema3.txt + Tema 3 - Extracción de características.pptx | K87: Dos partes: (1) estadísticos unidimensionales (población, muestra, tipos de variable, resumen de variables cualitativas y cuantitativas) y (2) características bidimensionales: la imagen como tabla de intensidades, procesado, segmentación, descriptores de forma y descriptores de textura. | L87: Cadena típica con imágenes: transformar intensidad o color, segmentar el objeto (máscara), medir descriptores y alimentar un modelo. | M87: El manual PDF no cubre este tema; la teoría está en el PowerPoint del profesor (en la carpeta CLASES) y la práctica en seis notebooks cuyas celdas de texto son solo títulos. | N87: ¿Por qué hay que segmentar antes de medir la forma de un objeto? | O87: Archivo 04 (notebooks) + PPTX 'Tema 3 - Extracción de características' (56 diapositivas).
A88: 3.1 | B88: 3. Extracción de características | C88: Conceptos básicos y variable estadística | D88: 1 | E88: ⚪ Pendiente | F88: Son las ideas básicas para describir datos con números. Población es todo lo que se quiere estudiar. Muestra es una parte representativa de ella. Variable es el valor que cada elemento toma para una característica concreta. | G88: Practicar identificando población/muestra/variable en ejemplos propios antes de pasar a variables cualitativas y cuantitativas. | H88: Media | I88: 27/09/2026 | J88: Tema 3 - Extracción de características.pptx (diap. 3-6) | K88: Población: conjunto de ítems que se desea estudiar. Muestra: subconjunto de la población; debe ser representativa, lo que se logra con muestreo aleatorio. Inferencia estadística: razonamiento que obtiene conclusiones, con margen de error conocido, sobre la población a partir de la muestra. Variable estadística: cualidad que poseen los individuos. | L88: Intención de voto: población = personas mayores de 18 años empadronadas; muestra = subconjunto equilibrado por sexo, edad y zona. | M88: Una muestra mal balanceada produce conclusiones erróneas. | N88: ¿Qué hace representativa a una muestra? | O88: PPTX diapositivas 3-6.
A89: 3.1.a | B89: 3. Extracción de características | C89: Población | D89: 2 | E89: ⚪ Pendiente | F89: Es el conjunto completo de elementos que se quiere estudiar o analizar, sean casos, personas o filas de una tabla. Por ejemplo, todos los lotes de un producto fabricado en masa. | H89: Baja | I89: 27/09/2026 | J89: pptx diap. 3 | K89: Población: conjunto de ítems (instancias, individuos, elementos, filas) que se desea estudiar o sobre el que se quieren extraer conclusiones. | L89: Todos los lotes de un producto que se fabricará en masa con un proceso industrial. | M89: No siempre se puede medir toda la población: de ahí la muestra. | N89: ¿Qué es la población en el ejemplo de la tarta de tres ingredientes? | O89: PPTX diapositivas 3-4.
A90: 3.1.b | B90: 3. Extracción de características | C90: Muestra y muestreo representativo | D90: 2 | E90: ⚪ Pendiente | F90: Es una parte de la población. Debe elegirse al azar para representarla bien y poder aplicar sus conclusiones a todos. Si está mal balanceada, por ejemplo en edad o sexo, las conclusiones pueden ser erróneas. | H90: Media | I90: 27/09/2026 | J90: pptx diap. 3-4 | K90: Muestra: cualquier subconjunto de la población; debe ser representativa, para lo cual se aplica muestreo aleatorio. El objetivo es conocer la población a partir del análisis de la muestra. | L90: Una porción de la tarta que contenga un trozo de cada ingrediente (fresa, nata, chocolate). | M90: Ejemplos de muestreo erróneo: muestras que omiten edades, sexos o ingredientes. | N90: ¿Por qué una porción con solo nata no representa la tarta? | O90: PPTX diapositivas 3-4.
A91: 3.1.c | B91: 3. Extracción de características | C91: Inferencia estadística | D91: 2 | E91: ⚪ Pendiente | F91: Es el razonamiento que permite sacar conclusiones sobre toda la población a partir de una muestra, con un margen de error conocido. Evita tener que estudiar a todos los elementos. | H91: Baja | I91: 27/09/2026 | J91: pptx diap. 3 | K91: Inferencia estadística: proceso de razonamiento por el que se obtienen conclusiones (con un margen de error conocido) sobre la población a partir del análisis de la muestra. | L91: Estimar el nivel educativo de Valencia a partir de 500 personas. | M91: La conclusión vale para la población solo si la muestra es representativa. | N91: ¿Qué garantiza la inferencia estadística respecto al error? | O91: PPTX diapositiva 3.
A92: 3.1.d | B92: 3. Extracción de características | C92: Variable estadística | D92: 2 | E92: ⚪ Pendiente | F92: Es una cualidad de los elementos estudiados. Es el valor que un elemento toma para una característica, como una columna de la tabla. Puede cambiar de un elemento a otro o con el tiempo. | H92: Media | I92: 27/09/2026 | J92: pptx diap. 5 | K92: Variable estadística: cada una de las cualidades que poseen los individuos de una población; el valor que toma una instancia para una característica. Tipos: nominales (modalidades no numéricas sin orden), ordinales (no numéricas con orden), discretas (valores contables) y continuas (infinitos valores en un rango). | L92: Cualitativas nominales: sexo, estado civil. Ordinales: puesto en un deporte, satisfacción. Cuantitativas discretas: número de hijos. Continuas: estatura, peso. | M92: Un código numérico de una categoría no la vuelve cuantitativa. | N92: ¿Es el número de hijos una variable discreta o continua? | O92: PPTX diapositivas 5-6.
A93: 3.2 | B93: 3. Extracción de características | C93: Análisis de variables cualitativas | D93: 1 | E93: ⚪ Pendiente | F93: Trata las variables que son categorías, como el nivel de estudios. Se cuenta cuántas veces aparece cada categoría y se muestra en gráficos. Así se resume la muestra sin tener que revisarla completa. | G93: Practicar construyendo una tabla de frecuencias y su gráfico de barras/sectores con una variable categórica propia. | H93: Media | I93: 27/09/2026 | J93: pptx diap. 7-8 + notebook var_cualitativas | K93: Variables cualitativas (categorías): se resumen con tablas de frecuencia y se representan con diagramas de barras y de sectores. | L93: Nivel de estudios: Secundaria, Bachillerato, Grado, Máster, Doctorado. | M93: Los códigos numéricos son etiquetas: la media de los códigos no tiene sentido. | N93: ¿Por qué la media de los códigos 1=secundaria y 2=grado no describe un nivel de estudios? | O93: PPTX diapositivas 7-8; notebook var_cualitativas.
A94: 3.2.a | B94: 3. Extracción de características | C94: Tablas de frecuencia | D94: 2 | E94: ⚪ Pendiente | F94: Es una tabla que cuenta cuántas veces aparece cada categoría en la muestra. Sirve para analizarla de forma ordenada. En código se obtiene con np.unique(datos, return_counts=True). | H94: Media | I94: 27/09/2026 | J94: pptx diap. 7 + notebook | K94: Tabla de frecuencia: resume una muestra de datos cualitativos contando cuántas veces aparece cada categoría (frecuencia absoluta). | L94: estudios, frecuencia = np.unique(nivel_estudios, return_counts=True). PPTX: muestra de K = 500 personas de 30 a 40 años de Valencia. | M94: Si las categorías son ordinales conserva su orden al presentar la tabla. | N94: ¿Qué devuelve np.unique con return_counts=True? | O94: PPTX diapositiva 7; notebook var_cualitativas.
A95: 3.2.b | B95: 3. Extracción de características | C95: Representación gráfica (barras y sectores) | D95: 2 | E95: ⚪ Pendiente | F95: Sirve para ver de un vistazo cuántas veces aparece cada categoría. En las barras, la altura muestra cuántas veces se repite cada una. En el gráfico de sectores (tipo pastel), cada porción muestra qué porcentaje del total le corresponde. | H95: Baja | I95: 27/09/2026 | J95: notebook var_cualitativas | K95: Diagrama de barras: la altura es la frecuencia de cada categoría. Diagrama de sectores (pastel): cada porción es el porcentaje del total. | L95: plt.bar(estudios, frecuencia); plt.pie(frecuencia, labels=estudios, autopct='%1.2f%%'). | M95: El sectores pierde legibilidad con muchas categorías. | N95: ¿Qué muestra la altura de una barra? | O95: PPTX diapositiva 8; notebook var_cualitativas.
A96: 3.3 | B96: 3. Extracción de características | C96: Análisis de variables cuantitativas | D96: 1 | E96: ⚪ Pendiente | F96: Son números que resumen una lista de datos numéricos mirándola desde cuatro lados: dónde está el centro, cómo quedan ordenados, cuánto se separan unos de otros y qué forma tiene el conjunto. Se estudian por separado para no confundirlos. | G96: Calcular las 4 familias de medidas sobre un mismo vector de datos y comparar qué aporta cada una. | H96: Alta | I96: 27/09/2026 | J96: pptx diap. 9-10 + notebook var_cuantitativas | K96: Cuatro familias de medidas: tendencia central (media, mediana, moda), posición (cuartiles, percentiles, RIC), dispersión (varianza, desviación típica) y distribución (asimetría y curtosis). | L96: X = [0.5, 23, 0.3, 4.5, 0.3, 0.5, -28, -50, 60, -100, -10, -11, 13, 19, 1, 9] del notebook. | M96: Los ejercicios del notebook (boxplot, iris) quedan sin resolver. | N96: ¿Qué pregunta responde cada una de las cuatro familias? | O96: PPTX diapositivas 9-10; notebook var_cuantitativas.
A97: 3.3.a | B97: 3. Extracción de características | C97: Medidas de tendencia central: media, mediana, moda | D97: 2 | E97: ⚪ Pendiente | F97: Son tres maneras de decir cuál es el valor típico de los datos. La media es el promedio de siempre. La mediana es el valor que queda justo en el medio al ordenarlos. La moda es el valor que más se repite. | H97: Alta | I97: 27/09/2026 | J97: pptx diap. 9 + notebook | K97: Media = (1/N) suma x_i. Mediana: valor central de los datos ordenados (si N es par, promedio de los dos centrales). Moda: valor más repetido. En código: np.mean, np.median, stats.mode. | L97: [2,2,2,2,12]: media 4, mediana 2, moda 2. | M97: La media se desplaza con valores extremos; la mediana resiste mejor. | N97: ¿Qué medida describe mejor al típico de [2,2,2,2,12] y por qué? | O97: PPTX diapositiva 9; notebook var_cuantitativas.
A98: 3.3.b | B98: 3. Extracción de características | C98: Medidas de posición: cuartiles, RIC y límites de outliers | D98: 2 | E98: ⚪ Pendiente | F98: Sirven para ubicar los datos y detectar valores raros. Los cuartiles cortan los datos ordenados en 4 partes. El rango intercuartílico (RIC) mide qué tan separados están los datos del 50% central. Con la regla 1.5·RIC se fijan límites; lo que cae fuera se considera un valor atípico (outlier), es decir, muy alejado del resto. | H98: Alta | I98: 27/09/2026 | J98: notebook var_cuantitativas | K98: Cuartiles Q1 (percentil 25) y Q3 (percentil 75); RIC = Q3 - Q1. Límites de outliers: inferior = Q1 - 1,5 RIC; superior = Q3 + 1,5 RIC. En código: np.percentile(X, 25), np.percentile(X, 75). | L98: lim_inf = Q1 - 1.5*RIC; lim_sup = Q3 + 1.5*RIC. | M98: El notebook propone dibujar el diagrama de cajas y bigotes, pero lo deja sin resolver. | N98: ¿Qué parte de los datos contiene el RIC? | O98: PPTX diapositiva 9; notebook var_cuantitativas.
A99: 3.3.c | B99: 3. Extracción de características | C99: Medidas de dispersión: varianza y desviación típica | D99: 2 | E99: ⚪ Pendiente | F99: Miden cuánto se alejan los datos, en promedio, de la media. La desviación típica es la raíz de la varianza y tiene las mismas unidades que el dato original, por eso es más fácil de interpretar. | H99: Alta | I99: 27/09/2026 | J99: pptx diap. 10 + notebook | K99: Desviación típica sigma = raíz de (suma (x_i - media)^2 / N); varianza = sigma al cuadrado. En código: np.std(X) (divide entre N por defecto) y varianza = desvest**2. | L99: Misma media con distintas dispersiones: [4,4,4,4] y [0,0,8,8] tienen media 4 pero desviaciones 0 y 4. | M99: La varianza muestral del tema 1 (1.8.c) divide entre n - 1; aquí, entre N. | N99: ¿Por qué la desviación típica es más fácil de interpretar que la varianza? | O99: PPTX diapositiva 10; notebook var_cuantitativas.
A100: 3.3.d | B100: 3. Extracción de características | C100: Medidas de distribución: asimetría y curtosis | D100: 2 | E100: ⚪ Pendiente | F100: Describen la forma que tiene el conjunto de datos. La asimetría indica si los datos se inclinan más hacia un lado de la media. La curtosis indica si la forma es más puntiaguda o más achatada que la curva normal (la típica forma de campana). | H100: Media | I100: 27/09/2026 | J100: notebook var_cuantitativas | K100: Asimetría A = suma (x_i - media)^3 / (N sigma^3): simetría respecto a la media. Curtosis K = suma (x_i - media)^4 / (N sigma^4) - 3: apuntamiento frente a la normal. K > 0 leptocúrtica; K = 0 mesocúrtica; K < 0 platicúrtica. En código: stats.skew(X) y stats.kurtosis(X, fisher=True). | L100: if curtosis > 0: leptocúrtica; elif curtosis < 0: platicúrtica; else mesocúrtica. | M100: El ejercicio final sobre iris queda sin resolver en el notebook. | N100: ¿Qué indica una curtosis positiva? | O100: PPTX diapositiva 10; notebook var_cuantitativas.
...
